Workbook

Sheet Menu
A1: Agregador de dados para o Imposto de Renda
A2: ="Ano-calendário "&Parâmetros!B4&" | Declaração do exercício "&Parâmetros!B5 -> Ano-calendário 2026 | Declaração do exercício 2027
A3: Dados de exemplo (fictícios) nas abas. Apague antes de usar com suas informações.
A5: Seção | B5: O que registrar | C5: Itens | D5: Pendências
A6: Contribuinte | B6: Nome, CPF e nascimento | C6: =IF(Contribuinte!B5<>"",1,0) -> 1 | D6: =Resumo!B34 -> 0
A7: Dependentes | B7: Quem entra como dependente | C7: =COUNTA(Dependentes!A6:A15) -> 1 | D7: =Resumo!B35 -> 0
A8: Rendimentos | B8: Informes de rendimentos recebidos no ano | C8: =SUMPRODUCT(--(Rendimentos!K6:K105<>"")) -> 4 | D8: =Resumo!B36+Resumo!B37 -> 1
A9: Deduções | B9: Saúde, educação, previdência e pensão | C9: =SUMPRODUCT(--(Deduções!I6:I155<>"")) -> 4 | D9: =Resumo!B39+Resumo!B40 -> 1
A10: Bens e Direitos | B10: Patrimônio em 31/12 dos dois anos | C10: =SUMPRODUCT(--('Bens e Direitos'!G6:G65<>"")) -> 2 | D10: =COUNTIF('Bens e Direitos'!G6:G65,"Revisar") -> 0
A11: Dívidas | B11: Financiamentos e empréstimos | C11: =SUMPRODUCT(--(Dívidas!F6:F35<>"")) -> 1 | D11: =COUNTIF(Dívidas!F6:F35,"Revisar") -> 0
A12: Checklist | B12: Documentos que precisam estar em mãos | C12: =SUMPRODUCT(--(Checklist!E6:E25<>"")) -> 12 | D12: =Resumo!B44 -> 0
A13: Resumo | B13: Totais, base estimada e verificações | D13: =Resumo!B46 -> 2
A14: Parâmetros | B14: Ano-calendário e limites de referência
A15: Listas | B15: Opções dos menus suspensos
A17: Situação geral
A18: =IF(Resumo!B46=0,"Sem pendências. Confira os avisos no Resumo antes de transmitir.","Pendências a resolver: "&Resumo!B46&". Avisos para conferir: "&Resumo!B47&".") -> Pendências a resolver: 2. Avisos para conferir: 1.
A20: Links rápidos (abrem no navegador)
A21: Meu Imposto de Renda (Receita Federal)
A22: Portal da Receita Federal
A23: e-CAC: consultas e documentos fiscais
A25: Ferramenta de organização. Não calcula o imposto devido nem substitui o programa da Receita Federal.

Sheet Contribuinte
A1: ◄ Voltar ao Menu
A2: Contribuinte
A3: Dados de identificação. O CPF é conferido pelos dígitos verificadores.
A4: Campo | B4: Informação | C4: Conferência
A5: Nome completo | B5: Fulano de Tal (exemplo) | C5: =IF(B5="","Preencher","OK") -> OK
A6: CPF | B6: 111.444.777-35 | C6: =IF(B6="","Preencher",IF(IFERROR(AND(LEN(SUBSTITUTE(SUBSTITUTE(SUBSTITUTE(SUBSTITUTE(B6,".",""),"-","")," ",""),"/",""))=11,SUBSTITUTE(SUBSTITUTE(SUBSTITUTE(SUBSTITUTE(B6,".",""),"-","")," ",""),"/","")<>REPT(LEFT(SUBSTITUTE(SUBSTITUTE(SUBSTITUTE(SUBSTITUTE(B6,".",""),"-","")," ",""),"/",""),1),11),VALUE(MID(SUBSTITUTE(SUBSTITUTE(SUBSTITUTE(SUBSTITUTE(B6,".",""),"-","")," ",""),"/",""),10,1))=IF(MOD(SUMPRODUCT(--MID(SUBSTITUTE(SUBSTITUTE(SUBSTITUTE(SUBSTITUTE(B6,".",""),"-","")," ",""),"/",""),{1,2,3,4,5,6,7,8,9},1),{10,9,8,7,6,5,4,3,2}),11)<2,0,11-MOD(SUMPRODUCT(--MID(SUBSTITUTE(SUBSTITUTE(SUBSTITUTE(SUBSTITUTE(B6,".",""),"-","")," ",""),"/",""),{1,2,3,4,5,6,7,8,9},1),{10,9,8,7,6,5,4,3,2}),11)),VALUE(MID(SUBSTITUTE(SUBSTITUTE(SUBSTITUTE(SUBSTITUTE(B6,".",""),"-","")," ",""),"/",""),11,1))=IF(MOD(SUMPRODUCT(--MID(SUBSTITUTE(SUBSTITUTE(SUBSTITUTE(SUBSTITUTE(B6,".",""),"-","")," ",""),"/",""),{1,2,3,4,5,6,7,8,9,10},1),{11,10,9,8,7,6,5,4,3,2}),11)<2,0,11-MOD(SUMPRODUCT(--MID(SUBSTITUTE(SUBSTITUTE(SUBSTITUTE(SUBSTITUTE(B6,".",""),"-","")," ",""),"/",""),{1,2,3,4,5,6,7,8,9,10},1),{11,10,9,8,7,6,5,4,3,2}),11))),FALSE()),"CPF válido","CPF inválido")) -> CPF válido
A7: Data de nascimento | B7: 29351 | C7: =IF(B7="","Preencher","OK") -> OK
A8: Ocupação principal | B8: Analista
A9: Município e UF | B9: São Paulo/SP
A11: Dados de exemplo (fictícios). Apague antes de usar.

Sheet Dependentes
A1: ◄ Voltar ao Menu
A2: Dependentes
A3: Até 10 dependentes. Cada um gera a dedução anual definida em Parâmetros.
A5: Nome | B5: CPF | C5: Data de nascimento | D5: Parentesco | E5: CPF válido? | F5: Status
A6: Filho Exemplo | B6: 529.982.247-25 | C6: 40983 | D6: Filho(a) ou enteado(a) | E6: =IF(B6="","",IF(IFERROR(AND(LEN(SUBSTITUTE(SUBSTITUTE(SUBSTITUTE(SUBSTITUTE(B6,".",""),"-","")," ",""),"/",""))=11,SUBSTITUTE(SUBSTITUTE(SUBSTITUTE(SUBSTITUTE(B6,".",""),"-","")," ",""),"/","")<>REPT(LEFT(SUBSTITUTE(SUBSTITUTE(SUBSTITUTE(SUBSTITUTE(B6,".",""),"-","")," ",""),"/",""),1),11),VALUE(MID(SUBSTITUTE(SUBSTITUTE(SUBSTITUTE(SUBSTITUTE(B6,".",""),"-","")," ",""),"/",""),10,1))=IF(MOD(SUMPRODUCT(--MID(SUBSTITUTE(SUBSTITUTE(SUBSTITUTE(SUBSTITUTE(B6,".",""),"-","")," ",""),"/",""),{1,2,3,4,5,6,7,8,9},1),{10,9,8,7,6,5,4,3,2}),11)<2,0,11-MOD(SUMPRODUCT(--MID(SUBSTITUTE(SUBSTITUTE(SUBSTITUTE(SUBSTITUTE(B6,".",""),"-","")," ",""),"/",""),{1,2,3,4,5,6,7,8,9},1),{10,9,8,7,6,5,4,3,2}),11)),VALUE(MID(SUBSTITUTE(SUBSTITUTE(SUBSTITUTE(SUBSTITUTE(B6,".",""),"-","")," ",""),"/",""),11,1))=IF(MOD(SUMPRODUCT(--MID(SUBSTITUTE(SUBSTITUTE(SUBSTITUTE(SUBSTITUTE(B6,".",""),"-","")," ",""),"/",""),{1,2,3,4,5,6,7,8,9,10},1),{11,10,9,8,7,6,5,4,3,2}),11)<2,0,11-MOD(SUMPRODUCT(--MID(SUBSTITUTE(SUBSTITUTE(SUBSTITUTE(SUBSTITUTE(B6,".",""),"-","")," ",""),"/",""),{1,2,3,4,5,6,7,8,9,10},1),{11,10,9,8,7,6,5,4,3,2}),11))),FALSE()),"Sim","Não")) -> Sim | F6: =IF(A6="","",IF(OR(B6="",C6="",D6="",E6="Não"),"Revisar","OK")) -> OK
E7: =IF(B7="","",IF(IFERROR(AND(LEN(SUBSTITUTE(SUBSTITUTE(SUBSTITUTE(SUBSTITUTE(B7,".",""),"-","")," ",""),"/",""))=11,SUBSTITUTE(SUBSTITUTE(SUBSTITUTE(SUBSTITUTE(B7,".",""),"-","")," ",""),"/","")<>REPT(LEFT(SUBSTITUTE(SUBSTITUTE(SUBSTITUTE(SUBSTITUTE(B7,".",""),"-","")," ",""),"/",""),1),11),VALUE(MID(SUBSTITUTE(SUBSTITUTE(SUBSTITUTE(SUBSTITUTE(B7,".",""),"-","")," ",""),"/",""),10,1))=IF(MOD(SUMPRODUCT(--MID(SUBSTITUTE(SUBSTITUTE(SUBSTITUTE(SUBSTITUTE(B7,".",""),"-","")," ",""),"/",""),{1,2,3,4,5,6,7,8,9},1),{10,9,8,7,6,5,4,3,2}),11)<2,0,11-MOD(SUMPRODUCT(--MID(SUBSTITUTE(SUBSTITUTE(SUBSTITUTE(SUBSTITUTE(B7,".",""),"-","")," ",""),"/",""),{1,2,3,4,5,6,7,8,9},1),{10,9,8,7,6,5,4,3,2}),11)),VALUE(MID(SUBSTITUTE(SUBSTITUTE(SUBSTITUTE(SUBSTITUTE(B7,".",""),"-","")," ",""),"/",""),11,1))=IF(MOD(SUMPRODUCT(--MID(SUBSTITUTE(SUBSTITUTE(SUBSTITUTE(SUBSTITUTE(B7,".",""),"-","")," ",""),"/",""),{1,2,3,4,5,6,7,8,9,10},1),{11,10,9,8,7,6,5,4,3,2}),11)<2,0,11-MOD(SUMPRODUCT(--MID(SUBSTITUTE(SUBSTITUTE(SUBSTITUTE(SUBSTITUTE(B7,".",""),"-","")," ",""),"/",""),{1,2,3,4,5,6,7,8,9,10},1),{11,10,9,8,7,6,5,4,3,2}),11))),FALSE()),"Sim","Não")) | F7: =IF(A7="","",IF(OR(B7="",C7="",D7="",E7="Não"),"Revisar","OK"))
E8: =IF(B8="","",IF(IFERROR(AND(LEN(SUBSTITUTE(SUBSTITUTE(SUBSTITUTE(SUBSTITUTE(B8,".",""),"-","")," ",""),"/",""))=11,SUBSTITUTE(SUBSTITUTE(SUBSTITUTE(SUBSTITUTE(B8,".",""),"-","")," ",""),"/","")<>REPT(LEFT(SUBSTITUTE(SUBSTITUTE(SUBSTITUTE(SUBSTITUTE(B8,".",""),"-","")," ",""),"/",""),1),11),VALUE(MID(SUBSTITUTE(SUBSTITUTE(SUBSTITUTE(SUBSTITUTE(B8,".",""),"-","")," ",""),"/",""),10,1))=IF(MOD(SUMPRODUCT(--MID(SUBSTITUTE(SUBSTITUTE(SUBSTITUTE(SUBSTITUTE(B8,".",""),"-","")," ",""),"/",""),{1,2,3,4,5,6,7,8,9},1),{10,9,8,7,6,5,4,3,2}),11)<2,0,11-MOD(SUMPRODUCT(--MID(SUBSTITUTE(SUBSTITUTE(SUBSTITUTE(SUBSTITUTE(B8,".",""),"-","")," ",""),"/",""),{1,2,3,4,5,6,7,8,9},1),{10,9,8,7,6,5,4,3,2}),11)),VALUE(MID(SUBSTITUTE(SUBSTITUTE(SUBSTITUTE(SUBSTITUTE(B8,".",""),"-","")," ",""),"/",""),11,1))=IF(MOD(SUMPRODUCT(--MID(SUBSTITUTE(SUBSTITUTE(SUBSTITUTE(SUBSTITUTE(B8,".",""),"-","")," ",""),"/",""),{1,2,3,4,5,6,7,8,9,10},1),{11,10,9,8,7,6,5,4,3,2}),11)<2,0,11-MOD(SUMPRODUCT(--MID(SUBSTITUTE(SUBSTITUTE(SUBSTITUTE(SUBSTITUTE(B8,".",""),"-","")," ",""),"/",""),{1,2,3,4,5,6,7,8,9,10},1),{11,10,9,8,7,6,5,4,3,2}),11))),FALSE()),"Sim","Não")) | F8: =IF(A8="","",IF(OR(B8="",C8="",D8="",E8="Não"),"Revisar","OK"))
E9: =IF(B9="","",IF(IFERROR(AND(LEN(SUBSTITUTE(SUBSTITUTE(SUBSTITUTE(SUBSTITUTE(B9,".",""),"-","")," ",""),"/",""))=11,SUBSTITUTE(SUBSTITUTE(SUBSTITUTE(SUBSTITUTE(B9,".",""),"-","")," ",""),"/","")<>REPT(LEFT(SUBSTITUTE(SUBSTITUTE(SUBSTITUTE(SUBSTITUTE(B9,".",""),"-","")," ",""),"/",""),1),11),VALUE(MID(SUBSTITUTE(SUBSTITUTE(SUBSTITUTE(SUBSTITUTE(B9,".",""),"-","")," ",""),"/",""),10,1))=IF(MOD(SUMPRODUCT(--MID(SUBSTITUTE(SUBSTITUTE(SUBSTITUTE(SUBSTITUTE(B9,".",""),"-","")," ",""),"/",""),{1,2,3,4,5,6,7,8,9},1),{10,9,8,7,6,5,4,3,2}),11)<2,0,11-MOD(SUMPRODUCT(--MID(SUBSTITUTE(SUBSTITUTE(SUBSTITUTE(SUBSTITUTE(B9,".",""),"-","")," ",""),"/",""),{1,2,3,4,5,6,7,8,9},1),{10,9,8,7,6,5,4,3,2}),11)),VALUE(MID(SUBSTITUTE(SUBSTITUTE(SUBSTITUTE(SUBSTITUTE(B9,".",""),"-","")," ",""),"/",""),11,1))=IF(MOD(SUMPRODUCT(--MID(SUBSTITUTE(SUBSTITUTE(SUBSTITUTE(SUBSTITUTE(B9,".",""),"-","")," ",""),"/",""),{1,2,3,4,5,6,7,8,9,10},1),{11,10,9,8,7,6,5,4,3,2}),11)<2,0,11-MOD(SUMPRODUCT(--MID(SUBSTITUTE(SUBSTITUTE(SUBSTITUTE(SUBSTITUTE(B9,".",""),"-","")," ",""),"/",""),{1,2,3,4,5,6,7,8,9,10},1),{11,10,9,8,7,6,5,4,3,2}),11))),FALSE()),"Sim","Não")) | F9: =IF(A9="","",IF(OR(B9="",C9="",D9="",E9="Não"),"Revisar","OK"))
E10: =IF(B10="","",IF(IFERROR(AND(LEN(SUBSTITUTE(SUBSTITUTE(SUBSTITUTE(SUBSTITUTE(B10,".",""),"-","")," ",""),"/",""))=11,SUBSTITUTE(SUBSTITUTE(SUBSTITUTE(SUBSTITUTE(B10,".",""),"-","")," ",""),"/","")<>REPT(LEFT(SUBSTITUTE(SUBSTITUTE(SUBSTITUTE(SUBSTITUTE(B10,".",""),"-","")," ",""),"/",""),1),11),VALUE(MID(SUBSTITUTE(SUBSTITUTE(SUBSTITUTE(SUBSTITUTE(B10,".",""),"-","")," ",""),"/",""),10,1))=IF(MOD(SUMPRODUCT(--MID(SUBSTITUTE(SUBSTITUTE(SUBSTITUTE(SUBSTITUTE(B10,".",""),"-","")," ",""),"/",""),{1,2,3,4,5,6,7,8,9},1),{10,9,8,7,6,5,4,3,2}),11)<2,0,11-MOD(SUMPRODUCT(--MID(SUBSTITUTE(SUBSTITUTE(SUBSTITUTE(SUBSTITUTE(B10,".",""),"-","")," ",""),"/",""),{1,2,3,4,5,6,7,8,9},1),{10,9,8,7,6,5,4,3,2}),11)),VALUE(MID(SUBSTITUTE(SUBSTITUTE(SUBSTITUTE(SUBSTITUTE(B10,".",""),"-","")," ",""),"/",""),11,1))=IF(MOD(SUMPRODUCT(--MID(SUBSTITUTE(SUBSTITUTE(SUBSTITUTE(SUBSTITUTE(B10,".",""),"-","")," ",""),"/",""),{1,2,3,4,5,6,7,8,9,10},1),{11,10,9,8,7,6,5,4,3,2}),11)<2,0,11-MOD(SUMPRODUCT(--MID(SUBSTITUTE(SUBSTITUTE(SUBSTITUTE(SUBSTITUTE(B10,".",""),"-","")," ",""),"/",""),{1,2,3,4,5,6,7,8,9,10},1),{11,10,9,8,7,6,5,4,3,2}),11))),FALSE()),"Sim","Não")) | F10: =IF(A10="","",IF(OR(B10="",C10="",D10="",E10="Não"),"Revisar","OK"))
E11: =IF(B11="","",IF(IFERROR(AND(LEN(SUBSTITUTE(SUBSTITUTE(SUBSTITUTE(SUBSTITUTE(B11,".",""),"-","")," ",""),"/",""))=11,SUBSTITUTE(SUBSTITUTE(SUBSTITUTE(SUBSTITUTE(B11,".",""),"-","")," ",""),"/","")<>REPT(LEFT(SUBSTITUTE(SUBSTITUTE(SUBSTITUTE(SUBSTITUTE(B11,".",""),"-","")," ",""),"/",""),1),11),VALUE(MID(SUBSTITUTE(SUBSTITUTE(SUBSTITUTE(SUBSTITUTE(B11,".",""),"-","")," ",""),"/",""),10,1))=IF(MOD(SUMPRODUCT(--MID(SUBSTITUTE(SUBSTITUTE(SUBSTITUTE(SUBSTITUTE(B11,".",""),"-","")," ",""),"/",""),{1,2,3,4,5,6,7,8,9},1),{10,9,8,7,6,5,4,3,2}),11)<2,0,11-MOD(SUMPRODUCT(--MID(SUBSTITUTE(SUBSTITUTE(SUBSTITUTE(SUBSTITUTE(B11,".",""),"-","")," ",""),"/",""),{1,2,3,4,5,6,7,8,9},1),{10,9,8,7,6,5,4,3,2}),11)),VALUE(MID(SUBSTITUTE(SUBSTITUTE(SUBSTITUTE(SUBSTITUTE(B11,".",""),"-","")," ",""),"/",""),11,1))=IF(MOD(SUMPRODUCT(--MID(SUBSTITUTE(SUBSTITUTE(SUBSTITUTE(SUBSTITUTE(B11,".",""),"-","")," ",""),"/",""),{1,2,3,4,5,6,7,8,9,10},1),{11,10,9,8,7,6,5,4,3,2}),11)<2,0,11-MOD(SUMPRODUCT(--MID(SUBSTITUTE(SUBSTITUTE(SUBSTITUTE(SUBSTITUTE(B11,".",""),"-","")," ",""),"/",""),{1,2,3,4,5,6,7,8,9,10},1),{11,10,9,8,7,6,5,4,3,2}),11))),FALSE()),"Sim","Não")) | F11: =IF(A11="","",IF(OR(B11="",C11="",D11="",E11="Não"),"Revisar","OK"))
E12: =IF(B12="","",IF(IFERROR(AND(LEN(SUBSTITUTE(SUBSTITUTE(SUBSTITUTE(SUBSTITUTE(B12,".",""),"-","")," ",""),"/",""))=11,SUBSTITUTE(SUBSTITUTE(SUBSTITUTE(SUBSTITUTE(B12,".",""),"-","")," ",""),"/","")<>REPT(LEFT(SUBSTITUTE(SUBSTITUTE(SUBSTITUTE(SUBSTITUTE(B12,".",""),"-","")," ",""),"/",""),1),11),VALUE(MID(SUBSTITUTE(SUBSTITUTE(SUBSTITUTE(SUBSTITUTE(B12,".",""),"-","")," ",""),"/",""),10,1))=IF(MOD(SUMPRODUCT(--MID(SUBSTITUTE(SUBSTITUTE(SUBSTITUTE(SUBSTITUTE(B12,".",""),"-","")," ",""),"/",""),{1,2,3,4,5,6,7,8,9},1),{10,9,8,7,6,5,4,3,2}),11)<2,0,11-MOD(SUMPRODUCT(--MID(SUBSTITUTE(SUBSTITUTE(SUBSTITUTE(SUBSTITUTE(B12,".",""),"-","")," ",""),"/",""),{1,2,3,4,5,6,7,8,9},1),{10,9,8,7,6,5,4,3,2}),11)),VALUE(MID(SUBSTITUTE(SUBSTITUTE(SUBSTITUTE(SUBSTITUTE(B12,".",""),"-","")," ",""),"/",""),11,1))=IF(MOD(SUMPRODUCT(--MID(SUBSTITUTE(SUBSTITUTE(SUBSTITUTE(SUBSTITUTE(B12,".",""),"-","")," ",""),"/",""),{1,2,3,4,5,6,7,8,9,10},1),{11,10,9,8,7,6,5,4,3,2}),11)<2,0,11-MOD(SUMPRODUCT(--MID(SUBSTITUTE(SUBSTITUTE(SUBSTITUTE(SUBSTITUTE(B12,".",""),"-","")," ",""),"/",""),{1,2,3,4,5,6,7,8,9,10},1),{11,10,9,8,7,6,5,4,3,2}),11))),FALSE()),"Sim","Não")) | F12: =IF(A12="","",IF(OR(B12="",C12="",D12="",E12="Não"),"Revisar","OK"))
E13: =IF(B13="","",IF(IFERROR(AND(LEN(SUBSTITUTE(SUBSTITUTE(SUBSTITUTE(SUBSTITUTE(B13,".",""),"-","")," ",""),"/",""))=11,SUBSTITUTE(SUBSTITUTE(SUBSTITUTE(SUBSTITUTE(B13,".",""),"-","")," ",""),"/","")<>REPT(LEFT(SUBSTITUTE(SUBSTITUTE(SUBSTITUTE(SUBSTITUTE(B13,".",""),"-","")," ",""),"/",""),1),11),VALUE(MID(SUBSTITUTE(SUBSTITUTE(SUBSTITUTE(SUBSTITUTE(B13,".",""),"-","")," ",""),"/",""),10,1))=IF(MOD(SUMPRODUCT(--MID(SUBSTITUTE(SUBSTITUTE(SUBSTITUTE(SUBSTITUTE(B13,".",""),"-","")," ",""),"/",""),{1,2,3,4,5,6,7,8,9},1),{10,9,8,7,6,5,4,3,2}),11)<2,0,11-MOD(SUMPRODUCT(--MID(SUBSTITUTE(SUBSTITUTE(SUBSTITUTE(SUBSTITUTE(B13,".",""),"-","")," ",""),"/",""),{1,2,3,4,5,6,7,8,9},1),{10,9,8,7,6,5,4,3,2}),11)),VALUE(MID(SUBSTITUTE(SUBSTITUTE(SUBSTITUTE(SUBSTITUTE(B13,".",""),"-","")," ",""),"/",""),11,1))=IF(MOD(SUMPRODUCT(--MID(SUBSTITUTE(SUBSTITUTE(SUBSTITUTE(SUBSTITUTE(B13,".",""),"-","")," ",""),"/",""),{1,2,3,4,5,6,7,8,9,10},1),{11,10,9,8,7,6,5,4,3,2}),11)<2,0,11-MOD(SUMPRODUCT(--MID(SUBSTITUTE(SUBSTITUTE(SUBSTITUTE(SUBSTITUTE(B13,".",""),"-","")," ",""),"/",""),{1,2,3,4,5,6,7,8,9,10},1),{11,10,9,8,7,6,5,4,3,2}),11))),FALSE()),"Sim","Não")) | F13: =IF(A13="","",IF(OR(B13="",C13="",D13="",E13="Não"),"Revisar","OK"))
E14: =IF(B14="","",IF(IFERROR(AND(LEN(SUBSTITUTE(SUBSTITUTE(SUBSTITUTE(SUBSTITUTE(B14,".",""),"-","")," ",""),"/",""))=11,SUBSTITUTE(SUBSTITUTE(SUBSTITUTE(SUBSTITUTE(B14,".",""),"-","")," ",""),"/","")<>REPT(LEFT(SUBSTITUTE(SUBSTITUTE(SUBSTITUTE(SUBSTITUTE(B14,".",""),"-","")," ",""),"/",""),1),11),VALUE(MID(SUBSTITUTE(SUBSTITUTE(SUBSTITUTE(SUBSTITUTE(B14,".",""),"-","")," ",""),"/",""),10,1))=IF(MOD(SUMPRODUCT(--MID(SUBSTITUTE(SUBSTITUTE(SUBSTITUTE(SUBSTITUTE(B14,".",""),"-","")," ",""),"/",""),{1,2,3,4,5,6,7,8,9},1),{10,9,8,7,6,5,4,3,2}),11)<2,0,11-MOD(SUMPRODUCT(--MID(SUBSTITUTE(SUBSTITUTE(SUBSTITUTE(SUBSTITUTE(B14,".",""),"-","")," ",""),"/",""),{1,2,3,4,5,6,7,8,9},1),{10,9,8,7,6,5,4,3,2}),11)),VALUE(MID(SUBSTITUTE(SUBSTITUTE(SUBSTITUTE(SUBSTITUTE(B14,".",""),"-","")," ",""),"/",""),11,1))=IF(MOD(SUMPRODUCT(--MID(SUBSTITUTE(SUBSTITUTE(SUBSTITUTE(SUBSTITUTE(B14,".",""),"-","")," ",""),"/",""),{1,2,3,4,5,6,7,8,9,10},1),{11,10,9,8,7,6,5,4,3,2}),11)<2,0,11-MOD(SUMPRODUCT(--MID(SUBSTITUTE(SUBSTITUTE(SUBSTITUTE(SUBSTITUTE(B14,".",""),"-","")," ",""),"/",""),{1,2,3,4,5,6,7,8,9,10},1),{11,10,9,8,7,6,5,4,3,2}),11))),FALSE()),"Sim","Não")) | F14: =IF(A14="","",IF(OR(B14="",C14="",D14="",E14="Não"),"Revisar","OK"))
E15: =IF(B15="","",IF(IFERROR(AND(LEN(SUBSTITUTE(SUBSTITUTE(SUBSTITUTE(SUBSTITUTE(B15,".",""),"-","")," ",""),"/",""))=11,SUBSTITUTE(SUBSTITUTE(SUBSTITUTE(SUBSTITUTE(B15,".",""),"-","")," ",""),"/","")<>REPT(LEFT(SUBSTITUTE(SUBSTITUTE(SUBSTITUTE(SUBSTITUTE(B15,".",""),"-","")," ",""),"/",""),1),11),VALUE(MID(SUBSTITUTE(SUBSTITUTE(SUBSTITUTE(SUBSTITUTE(B15,".",""),"-","")," ",""),"/",""),10,1))=IF(MOD(SUMPRODUCT(--MID(SUBSTITUTE(SUBSTITUTE(SUBSTITUTE(SUBSTITUTE(B15,".",""),"-","")," ",""),"/",""),{1,2,3,4,5,6,7,8,9},1),{10,9,8,7,6,5,4,3,2}),11)<2,0,11-MOD(SUMPRODUCT(--MID(SUBSTITUTE(SUBSTITUTE(SUBSTITUTE(SUBSTITUTE(B15,".",""),"-","")," ",""),"/",""),{1,2,3,4,5,6,7,8,9},1),{10,9,8,7,6,5,4,3,2}),11)),VALUE(MID(SUBSTITUTE(SUBSTITUTE(SUBSTITUTE(SUBSTITUTE(B15,".",""),"-","")," ",""),"/",""),11,1))=IF(MOD(SUMPRODUCT(--MID(SUBSTITUTE(SUBSTITUTE(SUBSTITUTE(SUBSTITUTE(B15,".",""),"-","")," ",""),"/",""),{1,2,3,4,5,6,7,8,9,10},1),{11,10,9,8,7,6,5,4,3,2}),11)<2,0,11-MOD(SUMPRODUCT(--MID(SUBSTITUTE(SUBSTITUTE(SUBSTITUTE(SUBSTITUTE(B15,".",""),"-","")," ",""),"/",""),{1,2,3,4,5,6,7,8,9,10},1),{11,10,9,8,7,6,5,4,3,2}),11))),FALSE()),"Sim","Não")) | F15: =IF(A15="","",IF(OR(B15="",C15="",D15="",E15="Não"),"Revisar","OK"))

Sheet Rendimentos
A1: ◄ Voltar ao Menu
A2: Rendimentos
A3: Um lançamento por fonte pagadora e tipo (use os totais do informe de rendimentos). A classe é preenchida sozinha.
A5: Data de referência | B5: Fonte pagadora | C5: CNPJ ou CPF da fonte | D5: Tipo de rendimento | E5: Classe (automática) | F5: Valor bruto (R$) | G5: Imposto retido (R$) | H5: INSS retido (R$) | I5: Informe recebido? | J5: Observação | K5: Status
A6: 46387 | B6: Empresa Exemplo Ltda | C6: 12.345.678/0001-95 | D6: Salário ou pró-labore | E6: =IF(D6="","",IFERROR(VLOOKUP(D6,Listas!$A$5:$B$16,2,FALSE()),"")) -> Tributável | F6: 78000 | G6: 4800 | H6: 8556 | I6: Sim | K6: =IF(AND(A6="",B6="",D6="",F6=""),"",IF(OR(A6="",B6="",D6="",F6="",NOT(IFERROR(OR(IFERROR(AND(LEN(SUBSTITUTE(SUBSTITUTE(SUBSTITUTE(SUBSTITUTE(C6,".",""),"-","")," ",""),"/",""))=11,SUBSTITUTE(SUBSTITUTE(SUBSTITUTE(SUBSTITUTE(C6,".",""),"-","")," ",""),"/","")<>REPT(LEFT(SUBSTITUTE(SUBSTITUTE(SUBSTITUTE(SUBSTITUTE(C6,".",""),"-","")," ",""),"/",""),1),11),VALUE(MID(SUBSTITUTE(SUBSTITUTE(SUBSTITUTE(SUBSTITUTE(C6,".",""),"-","")," ",""),"/",""),10,1))=IF(MOD(SUMPRODUCT(--MID(SUBSTITUTE(SUBSTITUTE(SUBSTITUTE(SUBSTITUTE(C6,".",""),"-","")," ",""),"/",""),{1,2,3,4,5,6,7,8,9},1),{10,9,8,7,6,5,4,3,2}),11)<2,0,11-MOD(SUMPRODUCT(--MID(SUBSTITUTE(SUBSTITUTE(SUBSTITUTE(SUBSTITUTE(C6,".",""),"-","")," ",""),"/",""),{1,2,3,4,5,6,7,8,9},1),{10,9,8,7,6,5,4,3,2}),11)),VALUE(MID(SUBSTITUTE(SUBSTITUTE(SUBSTITUTE(SUBSTITUTE(C6,".",""),"-","")," ",""),"/",""),11,1))=IF(MOD(SUMPRODUCT(--MID(SUBSTITUTE(SUBSTITUTE(SUBSTITUTE(SUBSTITUTE(C6,".",""),"-","")," ",""),"/",""),{1,2,3,4,5,6,7,8,9,10},1),{11,10,9,8,7,6,5,4,3,2}),11)<2,0,11-MOD(SUMPRODUCT(--MID(SUBSTITUTE(SUBSTITUTE(SUBSTITUTE(SUBSTITUTE(C6,".",""),"-","")," ",""),"/",""),{1,2,3,4,5,6,7,8,9,10},1),{11,10,9,8,7,6,5,4,3,2}),11))),FALSE()),AND(LEN(SUBSTITUTE(SUBSTITUTE(SUBSTITUTE(SUBSTITUTE(C6,".",""),"-","")," ",""),"/",""))=14,ISNUMBER(VALUE(SUBSTITUTE(SUBSTITUTE(SUBSTITUTE(SUBSTITUTE(C6,".",""),"-","")," ",""),"/",""))))),FALSE())),G6>F6),"Revisar",IF(I6<>"Sim","Falta informe","OK"))) -> OK
A7: 46387 | B7: Empresa Exemplo Ltda | C7: 12.345.678/0001-95 | D7: 13º salário | E7: =IF(D7="","",IFERROR(VLOOKUP(D7,Listas!$A$5:$B$16,2,FALSE()),"")) -> Exclusivo na fonte | F7: 6500 | G7: 350 | H7: 0 | I7: Sim | K7: =IF(AND(A7="",B7="",D7="",F7=""),"",IF(OR(A7="",B7="",D7="",F7="",NOT(IFERROR(OR(IFERROR(AND(LEN(SUBSTITUTE(SUBSTITUTE(SUBSTITUTE(SUBSTITUTE(C7,".",""),"-","")," ",""),"/",""))=11,SUBSTITUTE(SUBSTITUTE(SUBSTITUTE(SUBSTITUTE(C7,".",""),"-","")," ",""),"/","")<>REPT(LEFT(SUBSTITUTE(SUBSTITUTE(SUBSTITUTE(SUBSTITUTE(C7,".",""),"-","")," ",""),"/",""),1),11),VALUE(MID(SUBSTITUTE(SUBSTITUTE(SUBSTITUTE(SUBSTITUTE(C7,".",""),"-","")," ",""),"/",""),10,1))=IF(MOD(SUMPRODUCT(--MID(SUBSTITUTE(SUBSTITUTE(SUBSTITUTE(SUBSTITUTE(C7,".",""),"-","")," ",""),"/",""),{1,2,3,4,5,6,7,8,9},1),{10,9,8,7,6,5,4,3,2}),11)<2,0,11-MOD(SUMPRODUCT(--MID(SUBSTITUTE(SUBSTITUTE(SUBSTITUTE(SUBSTITUTE(C7,".",""),"-","")," ",""),"/",""),{1,2,3,4,5,6,7,8,9},1),{10,9,8,7,6,5,4,3,2}),11)),VALUE(MID(SUBSTITUTE(SUBSTITUTE(SUBSTITUTE(SUBSTITUTE(C7,".",""),"-","")," ",""),"/",""),11,1))=IF(MOD(SUMPRODUCT(--MID(SUBSTITUTE(SUBSTITUTE(SUBSTITUTE(SUBSTITUTE(C7,".",""),"-","")," ",""),"/",""),{1,2,3,4,5,6,7,8,9,10},1),{11,10,9,8,7,6,5,4,3,2}),11)<2,0,11-MOD(SUMPRODUCT(--MID(SUBSTITUTE(SUBSTITUTE(SUBSTITUTE(SUBSTITUTE(C7,".",""),"-","")," ",""),"/",""),{1,2,3,4,5,6,7,8,9,10},1),{11,10,9,8,7,6,5,4,3,2}),11))),FALSE()),AND(LEN(SUBSTITUTE(SUBSTITUTE(SUBSTITUTE(SUBSTITUTE(C7,".",""),"-","")," ",""),"/",""))=14,ISNUMBER(VALUE(SUBSTITUTE(SUBSTITUTE(SUBSTITUTE(SUBSTITUTE(C7,".",""),"-","")," ",""),"/",""))))),FALSE())),G7>F7),"Revisar",IF(I7<>"Sim","Falta informe","OK"))) -> OK
A8: 46387 | B8: Banco Exemplo S.A. | C8: 98.765.432/0001-10 | D8: Rendimento de aplicação financeira | E8: =IF(D8="","",IFERROR(VLOOKUP(D8,Listas!$A$5:$B$16,2,FALSE()),"")) -> Exclusivo na fonte | F8: 1200 | G8: 180 | H8: 0 | I8: Sim | K8: =IF(AND(A8="",B8="",D8="",F8=""),"",IF(OR(A8="",B8="",D8="",F8="",NOT(IFERROR(OR(IFERROR(AND(LEN(SUBSTITUTE(SUBSTITUTE(SUBSTITUTE(SUBSTITUTE(C8,".",""),"-","")," ",""),"/",""))=11,SUBSTITUTE(SUBSTITUTE(SUBSTITUTE(SUBSTITUTE(C8,".",""),"-","")," ",""),"/","")<>REPT(LEFT(SUBSTITUTE(SUBSTITUTE(SUBSTITUTE(SUBSTITUTE(C8,".",""),"-","")," ",""),"/",""),1),11),VALUE(MID(SUBSTITUTE(SUBSTITUTE(SUBSTITUTE(SUBSTITUTE(C8,".",""),"-","")," ",""),"/",""),10,1))=IF(MOD(SUMPRODUCT(--MID(SUBSTITUTE(SUBSTITUTE(SUBSTITUTE(SUBSTITUTE(C8,".",""),"-","")," ",""),"/",""),{1,2,3,4,5,6,7,8,9},1),{10,9,8,7,6,5,4,3,2}),11)<2,0,11-MOD(SUMPRODUCT(--MID(SUBSTITUTE(SUBSTITUTE(SUBSTITUTE(SUBSTITUTE(C8,".",""),"-","")," ",""),"/",""),{1,2,3,4,5,6,7,8,9},1),{10,9,8,7,6,5,4,3,2}),11)),VALUE(MID(SUBSTITUTE(SUBSTITUTE(SUBSTITUTE(SUBSTITUTE(C8,".",""),"-","")," ",""),"/",""),11,1))=IF(MOD(SUMPRODUCT(--MID(SUBSTITUTE(SUBSTITUTE(SUBSTITUTE(SUBSTITUTE(C8,".",""),"-","")," ",""),"/",""),{1,2,3,4,5,6,7,8,9,10},1),{11,10,9,8,7,6,5,4,3,2}),11)<2,0,11-MOD(SUMPRODUCT(--MID(SUBSTITUTE(SUBSTITUTE(SUBSTITUTE(SUBSTITUTE(C8,".",""),"-","")," ",""),"/",""),{1,2,3,4,5,6,7,8,9,10},1),{11,10,9,8,7,6,5,4,3,2}),11))),FALSE()),AND(LEN(SUBSTITUTE(SUBSTITUTE(SUBSTITUTE(SUBSTITUTE(C8,".",""),"-","")," ",""),"/",""))=14,ISNUMBER(VALUE(SUBSTITUTE(SUBSTITUTE(SUBSTITUTE(SUBSTITUTE(C8,".",""),"-","")," ",""),"/",""))))),FALSE())),G8>F8),"Revisar",IF(I8<>"Sim","Falta informe","OK"))) -> OK
A9: 46387 | B9: Empresa Exemplo Ltda | C9: 12.345.678/0001-95 | D9: Verbas rescisórias indenizatórias e FGTS | E9: =IF(D9="","",IFERROR(VLOOKUP(D9,Listas!$A$5:$B$16,2,FALSE()),"")) -> Isento ou não tributável | F9: 12000 | G9: 0 | H9: 0 | I9: Não | K9: =IF(AND(A9="",B9="",D9="",F9=""),"",IF(OR(A9="",B9="",D9="",F9="",NOT(IFERROR(OR(IFERROR(AND(LEN(SUBSTITUTE(SUBSTITUTE(SUBSTITUTE(SUBSTITUTE(C9,".",""),"-","")," ",""),"/",""))=11,SUBSTITUTE(SUBSTITUTE(SUBSTITUTE(SUBSTITUTE(C9,".",""),"-","")," ",""),"/","")<>REPT(LEFT(SUBSTITUTE(SUBSTITUTE(SUBSTITUTE(SUBSTITUTE(C9,".",""),"-","")," ",""),"/",""),1),11),VALUE(MID(SUBSTITUTE(SUBSTITUTE(SUBSTITUTE(SUBSTITUTE(C9,".",""),"-","")," ",""),"/",""),10,1))=IF(MOD(SUMPRODUCT(--MID(SUBSTITUTE(SUBSTITUTE(SUBSTITUTE(SUBSTITUTE(C9,".",""),"-","")," ",""),"/",""),{1,2,3,4,5,6,7,8,9},1),{10,9,8,7,6,5,4,3,2}),11)<2,0,11-MOD(SUMPRODUCT(--MID(SUBSTITUTE(SUBSTITUTE(SUBSTITUTE(SUBSTITUTE(C9,".",""),"-","")," ",""),"/",""),{1,2,3,4,5,6,7,8,9},1),{10,9,8,7,6,5,4,3,2}),11)),VALUE(MID(SUBSTITUTE(SUBSTITUTE(SUBSTITUTE(SUBSTITUTE(C9,".",""),"-","")," ",""),"/",""),11,1))=IF(MOD(SUMPRODUCT(--MID(SUBSTITUTE(SUBSTITUTE(SUBSTITUTE(SUBSTITUTE(C9,".",""),"-","")," ",""),"/",""),{1,2,3,4,5,6,7,8,9,10},1),{11,10,9,8,7,6,5,4,3,2}),11)<2,0,11-MOD(SUMPRODUCT(--MID(SUBSTITUTE(SUBSTITUTE(SUBSTITUTE(SUBSTITUTE(C9,".",""),"-","")," ",""),"/",""),{1,2,3,4,5,6,7,8,9,10},1),{11,10,9,8,7,6,5,4,3,2}),11))),FALSE()),AND(LEN(SUBSTITUTE(SUBSTITUTE(SUBSTITUTE(SUBSTITUTE(C9,".",""),"-","")," ",""),"/",""))=14,ISNUMBER(VALUE(SUBSTITUTE(SUBSTITUTE(SUBSTITUTE(SUBSTITUTE(C9,".",""),"-","")," ",""),"/",""))))),FALSE())),G9>F9),"Revisar",IF(I9<>"Sim","Falta informe","OK"))) -> Falta informe
E10: =IF(D10="","",IFERROR(VLOOKUP(D10,Listas!$A$5:$B$16,2,FALSE()),"")) | K10: =IF(AND(A10="",B10="",D10="",F10=""),"",IF(OR(A10="",B10="",D10="",F10="",NOT(IFERROR(OR(IFERROR(AND(LEN(SUBSTITUTE(SUBSTITUTE(SUBSTITUTE(SUBSTITUTE(C10,".",""),"-","")," ",""),"/",""))=11,SUBSTITUTE(SUBSTITUTE(SUBSTITUTE(SUBSTITUTE(C10,".",""),"-","")," ",""),"/","")<>REPT(LEFT(SUBSTITUTE(SUBSTITUTE(SUBSTITUTE(SUBSTITUTE(C10,".",""),"-","")," ",""),"/",""),1),11),VALUE(MID(SUBSTITUTE(SUBSTITUTE(SUBSTITUTE(SUBSTITUTE(C10,".",""),"-","")," ",""),"/",""),10,1))=IF(MOD(SUMPRODUCT(--MID(SUBSTITUTE(SUBSTITUTE(SUBSTITUTE(SUBSTITUTE(C10,".",""),"-","")," ",""),"/",""),{1,2,3,4,5,6,7,8,9},1),{10,9,8,7,6,5,4,3,2}),11)<2,0,11-MOD(SUMPRODUCT(--MID(SUBSTITUTE(SUBSTITUTE(SUBSTITUTE(SUBSTITUTE(C10,".",""),"-","")," ",""),"/",""),{1,2,3,4,5,6,7,8,9},1),{10,9,8,7,6,5,4,3,2}),11)),VALUE(MID(SUBSTITUTE(SUBSTITUTE(SUBSTITUTE(SUBSTITUTE(C10,".",""),"-","")," ",""),"/",""),11,1))=IF(MOD(SUMPRODUCT(--MID(SUBSTITUTE(SUBSTITUTE(SUBSTITUTE(SUBSTITUTE(C10,".",""),"-","")," ",""),"/",""),{1,2,3,4,5,6,7,8,9,10},1),{11,10,9,8,7,6,5,4,3,2}),11)<2,0,11-MOD(SUMPRODUCT(--MID(SUBSTITUTE(SUBSTITUTE(SUBSTITUTE(SUBSTITUTE(C10,".",""),"-","")," ",""),"/",""),{1,2,3,4,5,6,7,8,9,10},1),{11,10,9,8,7,6,5,4,3,2}),11))),FALSE()),AND(LEN(SUBSTITUTE(SUBSTITUTE(SUBSTITUTE(SUBSTITUTE(C10,".",""),"-","")," ",""),"/",""))=14,ISNUMBER(VALUE(SUBSTITUTE(SUBSTITUTE(SUBSTITUTE(SUBSTITUTE(C10,".",""),"-","")," ",""),"/",""))))),FALSE())),G10>F10),"Revisar",IF(I10<>"Sim","Falta informe","OK")))
E11: =IF(D11="","",IFERROR(VLOOKUP(D11,Listas!$A$5:$B$16,2,FALSE()),"")) | K11: =IF(AND(A11="",B11="",D11="",F11=""),"",IF(OR(A11="",B11="",D11="",F11="",NOT(IFERROR(OR(IFERROR(AND(LEN(SUBSTITUTE(SUBSTITUTE(SUBSTITUTE(SUBSTITUTE(C11,".",""),"-","")," ",""),"/",""))=11,SUBSTITUTE(SUBSTITUTE(SUBSTITUTE(SUBSTITUTE(C11,".",""),"-","")," ",""),"/","")<>REPT(LEFT(SUBSTITUTE(SUBSTITUTE(SUBSTITUTE(SUBSTITUTE(C11,".",""),"-","")," ",""),"/",""),1),11),VALUE(MID(SUBSTITUTE(SUBSTITUTE(SUBSTITUTE(SUBSTITUTE(C11,".",""),"-","")," ",""),"/",""),10,1))=IF(MOD(SUMPRODUCT(--MID(SUBSTITUTE(SUBSTITUTE(SUBSTITUTE(SUBSTITUTE(C11,".",""),"-","")," ",""),"/",""),{1,2,3,4,5,6,7,8,9},1),{10,9,8,7,6,5,4,3,2}),11)<2,0,11-MOD(SUMPRODUCT(--MID(SUBSTITUTE(SUBSTITUTE(SUBSTITUTE(SUBSTITUTE(C11,".",""),"-","")," ",""),"/",""),{1,2,3,4,5,6,7,8,9},1),{10,9,8,7,6,5,4,3,2}),11)),VALUE(MID(SUBSTITUTE(SUBSTITUTE(SUBSTITUTE(SUBSTITUTE(C11,".",""),"-","")," ",""),"/",""),11,1))=IF(MOD(SUMPRODUCT(--MID(SUBSTITUTE(SUBSTITUTE(SUBSTITUTE(SUBSTITUTE(C11,".",""),"-","")," ",""),"/",""),{1,2,3,4,5,6,7,8,9,10},1),{11,10,9,8,7,6,5,4,3,2}),11)<2,0,11-MOD(SUMPRODUCT(--MID(SUBSTITUTE(SUBSTITUTE(SUBSTITUTE(SUBSTITUTE(C11,".",""),"-","")," ",""),"/",""),{1,2,3,4,5,6,7,8,9,10},1),{11,10,9,8,7,6,5,4,3,2}),11))),FALSE()),AND(LEN(SUBSTITUTE(SUBSTITUTE(SUBSTITUTE(SUBSTITUTE(C11,".",""),"-","")," ",""),"/",""))=14,ISNUMBER(VALUE(SUBSTITUTE(SUBSTITUTE(SUBSTITUTE(SUBSTITUTE(C11,".",""),"-","")," ",""),"/",""))))),FALSE())),G11>F11),"Revisar",IF(I11<>"Sim","Falta informe","OK")))
E12: =IF(D12="","",IFERROR(VLOOKUP(D12,Listas!$A$5:$B$16,2,FALSE()),"")) | K12: =IF(AND(A12="",B12="",D12="",F12=""),"",IF(OR(A12="",B12="",D12="",F12="",NOT(IFERROR(OR(IFERROR(AND(LEN(SUBSTITUTE(SUBSTITUTE(SUBSTITUTE(SUBSTITUTE(C12,".",""),"-","")," ",""),"/",""))=11,SUBSTITUTE(SUBSTITUTE(SUBSTITUTE(SUBSTITUTE(C12,".",""),"-","")," ",""),"/","")<>REPT(LEFT(SUBSTITUTE(SUBSTITUTE(SUBSTITUTE(SUBSTITUTE(C12,".",""),"-","")," ",""),"/",""),1),11),VALUE(MID(SUBSTITUTE(SUBSTITUTE(SUBSTITUTE(SUBSTITUTE(C12,".",""),"-","")," ",""),"/",""),10,1))=IF(MOD(SUMPRODUCT(--MID(SUBSTITUTE(SUBSTITUTE(SUBSTITUTE(SUBSTITUTE(C12,".",""),"-","")," ",""),"/",""),{1,2,3,4,5,6,7,8,9},1),{10,9,8,7,6,5,4,3,2}),11)<2,0,11-MOD(SUMPRODUCT(--MID(SUBSTITUTE(SUBSTITUTE(SUBSTITUTE(SUBSTITUTE(C12,".",""),"-","")," ",""),"/",""),{1,2,3,4,5,6,7,8,9},1),{10,9,8,7,6,5,4,3,2}),11)),VALUE(MID(SUBSTITUTE(SUBSTITUTE(SUBSTITUTE(SUBSTITUTE(C12,".",""),"-","")," ",""),"/",""),11,1))=IF(MOD(SUMPRODUCT(--MID(SUBSTITUTE(SUBSTITUTE(SUBSTITUTE(SUBSTITUTE(C12,".",""),"-","")," ",""),"/",""),{1,2,3,4,5,6,7,8,9,10},1),{11,10,9,8,7,6,5,4,3,2}),11)<2,0,11-MOD(SUMPRODUCT(--MID(SUBSTITUTE(SUBSTITUTE(SUBSTITUTE(SUBSTITUTE(C12,".",""),"-","")," ",""),"/",""),{1,2,3,4,5,6,7,8,9,10},1),{11,10,9,8,7,6,5,4,3,2}),11))),FALSE()),AND(LEN(SUBSTITUTE(SUBSTITUTE(SUBSTITUTE(SUBSTITUTE(C12,".",""),"-","")," ",""),"/",""))=14,ISNUMBER(VALUE(SUBSTITUTE(SUBSTITUTE(SUBSTITUTE(SUBSTITUTE(C12,".",""),"-","")," ",""),"/",""))))),FALSE())),G12>F12),"Revisar",IF(I12<>"Sim","Falta informe","OK")))
E13: =IF(D13="","",IFERROR(VLOOKUP(D13,Listas!$A$5:$B$16,2,FALSE()),"")) | K13: =IF(AND(A13="",B13="",D13="",F13=""),"",IF(OR(A13="",B13="",D13="",F13="",NOT(IFERROR(OR(IFERROR(AND(LEN(SUBSTITUTE(SUBSTITUTE(SUBSTITUTE(SUBSTITUTE(C13,".",""),"-","")," ",""),"/",""))=11,SUBSTITUTE(SUBSTITUTE(SUBSTITUTE(SUBSTITUTE(C13,".",""),"-","")," ",""),"/","")<>REPT(LEFT(SUBSTITUTE(SUBSTITUTE(SUBSTITUTE(SUBSTITUTE(C13,".",""),"-","")," ",""),"/",""),1),11),VALUE(MID(SUBSTITUTE(SUBSTITUTE(SUBSTITUTE(SUBSTITUTE(C13,".",""),"-","")," ",""),"/",""),10,1))=IF(MOD(SUMPRODUCT(--MID(SUBSTITUTE(SUBSTITUTE(SUBSTITUTE(SUBSTITUTE(C13,".",""),"-","")," ",""),"/",""),{1,2,3,4,5,6,7,8,9},1),{10,9,8,7,6,5,4,3,2}),11)<2,0,11-MOD(SUMPRODUCT(--MID(SUBSTITUTE(SUBSTITUTE(SUBSTITUTE(SUBSTITUTE(C13,".",""),"-","")," ",""),"/",""),{1,2,3,4,5,6,7,8,9},1),{10,9,8,7,6,5,4,3,2}),11)),VALUE(MID(SUBSTITUTE(SUBSTITUTE(SUBSTITUTE(SUBSTITUTE(C13,".",""),"-","")," ",""),"/",""),11,1))=IF(MOD(SUMPRODUCT(--MID(SUBSTITUTE(SUBSTITUTE(SUBSTITUTE(SUBSTITUTE(C13,".",""),"-","")," ",""),"/",""),{1,2,3,4,5,6,7,8,9,10},1),{11,10,9,8,7,6,5,4,3,2}),11)<2,0,11-MOD(SUMPRODUCT(--MID(SUBSTITUTE(SUBSTITUTE(SUBSTITUTE(SUBSTITUTE(C13,".",""),"-","")," ",""),"/",""),{1,2,3,4,5,6,7,8,9,10},1),{11,10,9,8,7,6,5,4,3,2}),11))),FALSE()),AND(LEN(SUBSTITUTE(SUBSTITUTE(SUBSTITUTE(SUBSTITUTE(C13,".",""),"-","")," ",""),"/",""))=14,ISNUMBER(VALUE(SUBSTITUTE(SUBSTITUTE(SUBSTITUTE(SUBSTITUTE(C13,".",""),"-","")," ",""),"/",""))))),FALSE())),G13>F13),"Revisar",IF(I13<>"Sim","Falta informe","OK")))
E14: =IF(D14="","",IFERROR(VLOOKUP(D14,Listas!$A$5:$B$16,2,FALSE()),"")) | K14: =IF(AND(A14="",B14="",D14="",F14=""),"",IF(OR(A14="",B14="",D14="",F14="",NOT(IFERROR(OR(IFERROR(AND(LEN(SUBSTITUTE(SUBSTITUTE(SUBSTITUTE(SUBSTITUTE(C14,".",""),"-","")," ",""),"/",""))=11,SUBSTITUTE(SUBSTITUTE(SUBSTITUTE(SUBSTITUTE(C14,".",""),"-","")," ",""),"/","")<>REPT(LEFT(SUBSTITUTE(SUBSTITUTE(SUBSTITUTE(SUBSTITUTE(C14,".",""),"-","")," ",""),"/",""),1),11),VALUE(MID(SUBSTITUTE(SUBSTITUTE(SUBSTITUTE(SUBSTITUTE(C14,".",""),"-","")," ",""),"/",""),10,1))=IF(MOD(SUMPRODUCT(--MID(SUBSTITUTE(SUBSTITUTE(SUBSTITUTE(SUBSTITUTE(C14,".",""),"-","")," ",""),"/",""),{1,2,3,4,5,6,7,8,9},1),{10,9,8,7,6,5,4,3,2}),11)<2,0,11-MOD(SUMPRODUCT(--MID(SUBSTITUTE(SUBSTITUTE(SUBSTITUTE(SUBSTITUTE(C14,".",""),"-","")," ",""),"/",""),{1,2,3,4,5,6,7,8,9},1),{10,9,8,7,6,5,4,3,2}),11)),VALUE(MID(SUBSTITUTE(SUBSTITUTE(SUBSTITUTE(SUBSTITUTE(C14,".",""),"-","")," ",""),"/",""),11,1))=IF(MOD(SUMPRODUCT(--MID(SUBSTITUTE(SUBSTITUTE(SUBSTITUTE(SUBSTITUTE(C14,".",""),"-","")," ",""),"/",""),{1,2,3,4,5,6,7,8,9,10},1),{11,10,9,8,7,6,5,4,3,2}),11)<2,0,11-MOD(SUMPRODUCT(--MID(SUBSTITUTE(SUBSTITUTE(SUBSTITUTE(SUBSTITUTE(C14,".",""),"-","")," ",""),"/",""),{1,2,3,4,5,6,7,8,9,10},1),{11,10,9,8,7,6,5,4,3,2}),11))),FALSE()),AND(LEN(SUBSTITUTE(SUBSTITUTE(SUBSTITUTE(SUBSTITUTE(C14,".",""),"-","")," ",""),"/",""))=14,ISNUMBER(VALUE(SUBSTITUTE(SUBSTITUTE(SUBSTITUTE(SUBSTITUTE(C14,".",""),"-","")," ",""),"/",""))))),FALSE())),G14>F14),"Revisar",IF(I14<>"Sim","Falta informe","OK")))
E15: =IF(D15="","",IFERROR(VLOOKUP(D15,Listas!$A$5:$B$16,2,FALSE()),"")) | K15: =IF(AND(A15="",B15="",D15="",F15=""),"",IF(OR(A15="",B15="",D15="",F15="",NOT(IFERROR(OR(IFERROR(AND(LEN(SUBSTITUTE(SUBSTITUTE(SUBSTITUTE(SUBSTITUTE(C15,".",""),"-","")," ",""),"/",""))=11,SUBSTITUTE(SUBSTITUTE(SUBSTITUTE(SUBSTITUTE(C15,".",""),"-","")," ",""),"/","")<>REPT(LEFT(SUBSTITUTE(SUBSTITUTE(SUBSTITUTE(SUBSTITUTE(C15,".",""),"-","")," ",""),"/",""),1),11),VALUE(MID(SUBSTITUTE(SUBSTITUTE(SUBSTITUTE(SUBSTITUTE(C15,".",""),"-","")," ",""),"/",""),10,1))=IF(MOD(SUMPRODUCT(--MID(SUBSTITUTE(SUBSTITUTE(SUBSTITUTE(SUBSTITUTE(C15,".",""),"-","")," ",""),"/",""),{1,2,3,4,5,6,7,8,9},1),{10,9,8,7,6,5,4,3,2}),11)<2,0,11-MOD(SUMPRODUCT(--MID(SUBSTITUTE(SUBSTITUTE(SUBSTITUTE(SUBSTITUTE(C15,".",""),"-","")," ",""),"/",""),{1,2,3,4,5,6,7,8,9},1),{10,9,8,7,6,5,4,3,2}),11)),VALUE(MID(SUBSTITUTE(SUBSTITUTE(SUBSTITUTE(SUBSTITUTE(C15,".",""),"-","")," ",""),"/",""),11,1))=IF(MOD(SUMPRODUCT(--MID(SUBSTITUTE(SUBSTITUTE(SUBSTITUTE(SUBSTITUTE(C15,".",""),"-","")," ",""),"/",""),{1,2,3,4,5,6,7,8,9,10},1),{11,10,9,8,7,6,5,4,3,2}),11)<2,0,11-MOD(SUMPRODUCT(--MID(SUBSTITUTE(SUBSTITUTE(SUBSTITUTE(SUBSTITUTE(C15,".",""),"-","")," ",""),"/",""),{1,2,3,4,5,6,7,8,9,10},1),{11,10,9,8,7,6,5,4,3,2}),11))),FALSE()),AND(LEN(SUBSTITUTE(SUBSTITUTE(SUBSTITUTE(SUBSTITUTE(C15,".",""),"-","")," ",""),"/",""))=14,ISNUMBER(VALUE(SUBSTITUTE(SUBSTITUTE(SUBSTITUTE(SUBSTITUTE(C15,".",""),"-","")," ",""),"/",""))))),FALSE())),G15>F15),"Revisar",IF(I15<>"Sim","Falta informe","OK")))
E16: =IF(D16="","",IFERROR(VLOOKUP(D16,Listas!$A$5:$B$16,2,FALSE()),"")) | K16: =IF(AND(A16="",B16="",D16="",F16=""),"",IF(OR(A16="",B16="",D16="",F16="",NOT(IFERROR(OR(IFERROR(AND(LEN(SUBSTITUTE(SUBSTITUTE(SUBSTITUTE(SUBSTITUTE(C16,".",""),"-","")," ",""),"/",""))=11,SUBSTITUTE(SUBSTITUTE(SUBSTITUTE(SUBSTITUTE(C16,".",""),"-","")," ",""),"/","")<>REPT(LEFT(SUBSTITUTE(SUBSTITUTE(SUBSTITUTE(SUBSTITUTE(C16,".",""),"-","")," ",""),"/",""),1),11),VALUE(MID(SUBSTITUTE(SUBSTITUTE(SUBSTITUTE(SUBSTITUTE(C16,".",""),"-","")," ",""),"/",""),10,1))=IF(MOD(SUMPRODUCT(--MID(SUBSTITUTE(SUBSTITUTE(SUBSTITUTE(SUBSTITUTE(C16,".",""),"-","")," ",""),"/",""),{1,2,3,4,5,6,7,8,9},1),{10,9,8,7,6,5,4,3,2}),11)<2,0,11-MOD(SUMPRODUCT(--MID(SUBSTITUTE(SUBSTITUTE(SUBSTITUTE(SUBSTITUTE(C16,".",""),"-","")," ",""),"/",""),{1,2,3,4,5,6,7,8,9},1),{10,9,8,7,6,5,4,3,2}),11)),VALUE(MID(SUBSTITUTE(SUBSTITUTE(SUBSTITUTE(SUBSTITUTE(C16,".",""),"-","")," ",""),"/",""),11,1))=IF(MOD(SUMPRODUCT(--MID(SUBSTITUTE(SUBSTITUTE(SUBSTITUTE(SUBSTITUTE(C16,".",""),"-","")," ",""),"/",""),{1,2,3,4,5,6,7,8,9,10},1),{11,10,9,8,7,6,5,4,3,2}),11)<2,0,11-MOD(SUMPRODUCT(--MID(SUBSTITUTE(SUBSTITUTE(SUBSTITUTE(SUBSTITUTE(C16,".",""),"-","")," ",""),"/",""),{1,2,3,4,5,6,7,8,9,10},1),{11,10,9,8,7,6,5,4,3,2}),11))),FALSE()),AND(LEN(SUBSTITUTE(SUBSTITUTE(SUBSTITUTE(SUBSTITUTE(C16,".",""),"-","")," ",""),"/",""))=14,ISNUMBER(VALUE(SUBSTITUTE(SUBSTITUTE(SUBSTITUTE(SUBSTITUTE(C16,".",""),"-","")," ",""),"/",""))))),FALSE())),G16>F16),"Revisar",IF(I16<>"Sim","Falta informe","OK")))
E17: =IF(D17="","",IFERROR(VLOOKUP(D17,Listas!$A$5:$B$16,2,FALSE()),"")) | K17: =IF(AND(A17="",B17="",D17="",F17=""),"",IF(OR(A17="",B17="",D17="",F17="",NOT(IFERROR(OR(IFERROR(AND(LEN(SUBSTITUTE(SUBSTITUTE(SUBSTITUTE(SUBSTITUTE(C17,".",""),"-","")," ",""),"/",""))=11,SUBSTITUTE(SUBSTITUTE(SUBSTITUTE(SUBSTITUTE(C17,".",""),"-","")," ",""),"/","")<>REPT(LEFT(SUBSTITUTE(SUBSTITUTE(SUBSTITUTE(SUBSTITUTE(C17,".",""),"-","")," ",""),"/",""),1),11),VALUE(MID(SUBSTITUTE(SUBSTITUTE(SUBSTITUTE(SUBSTITUTE(C17,".",""),"-","")," ",""),"/",""),10,1))=IF(MOD(SUMPRODUCT(--MID(SUBSTITUTE(SUBSTITUTE(SUBSTITUTE(SUBSTITUTE(C17,".",""),"-","")," ",""),"/",""),{1,2,3,4,5,6,7,8,9},1),{10,9,8,7,6,5,4,3,2}),11)<2,0,11-MOD(SUMPRODUCT(--MID(SUBSTITUTE(SUBSTITUTE(SUBSTITUTE(SUBSTITUTE(C17,".",""),"-","")," ",""),"/",""),{1,2,3,4,5,6,7,8,9},1),{10,9,8,7,6,5,4,3,2}),11)),VALUE(MID(SUBSTITUTE(SUBSTITUTE(SUBSTITUTE(SUBSTITUTE(C17,".",""),"-","")," ",""),"/",""),11,1))=IF(MOD(SUMPRODUCT(--MID(SUBSTITUTE(SUBSTITUTE(SUBSTITUTE(SUBSTITUTE(C17,".",""),"-","")," ",""),"/",""),{1,2,3,4,5,6,7,8,9,10},1),{11,10,9,8,7,6,5,4,3,2}),11)<2,0,11-MOD(SUMPRODUCT(--MID(SUBSTITUTE(SUBSTITUTE(SUBSTITUTE(SUBSTITUTE(C17,".",""),"-","")," ",""),"/",""),{1,2,3,4,5,6,7,8,9,10},1),{11,10,9,8,7,6,5,4,3,2}),11))),FALSE()),AND(LEN(SUBSTITUTE(SUBSTITUTE(SUBSTITUTE(SUBSTITUTE(C17,".",""),"-","")," ",""),"/",""))=14,ISNUMBER(VALUE(SUBSTITUTE(SUBSTITUTE(SUBSTITUTE(SUBSTITUTE(C17,".",""),"-","")," ",""),"/",""))))),FALSE())),G17>F17),"Revisar",IF(I17<>"Sim","Falta informe","OK")))
E18: =IF(D18="","",IFERROR(VLOOKUP(D18,Listas!$A$5:$B$16,2,FALSE()),"")) | K18: =IF(AND(A18="",B18="",D18="",F18=""),"",IF(OR(A18="",B18="",D18="",F18="",NOT(IFERROR(OR(IFERROR(AND(LEN(SUBSTITUTE(SUBSTITUTE(SUBSTITUTE(SUBSTITUTE(C18,".",""),"-","")," ",""),"/",""))=11,SUBSTITUTE(SUBSTITUTE(SUBSTITUTE(SUBSTITUTE(C18,".",""),"-","")," ",""),"/","")<>REPT(LEFT(SUBSTITUTE(SUBSTITUTE(SUBSTITUTE(SUBSTITUTE(C18,".",""),"-","")," ",""),"/",""),1),11),VALUE(MID(SUBSTITUTE(SUBSTITUTE(SUBSTITUTE(SUBSTITUTE(C18,".",""),"-","")," ",""),"/",""),10,1))=IF(MOD(SUMPRODUCT(--MID(SUBSTITUTE(SUBSTITUTE(SUBSTITUTE(SUBSTITUTE(C18,".",""),"-","")," ",""),"/",""),{1,2,3,4,5,6,7,8,9},1),{10,9,8,7,6,5,4,3,2}),11)<2,0,11-MOD(SUMPRODUCT(--MID(SUBSTITUTE(SUBSTITUTE(SUBSTITUTE(SUBSTITUTE(C18,".",""),"-","")," ",""),"/",""),{1,2,3,4,5,6,7,8,9},1),{10,9,8,7,6,5,4,3,2}),11)),VALUE(MID(SUBSTITUTE(SUBSTITUTE(SUBSTITUTE(SUBSTITUTE(C18,".",""),"-","")," ",""),"/",""),11,1))=IF(MOD(SUMPRODUCT(--MID(SUBSTITUTE(SUBSTITUTE(SUBSTITUTE(SUBSTITUTE(C18,".",""),"-","")," ",""),"/",""),{1,2,3,4,5,6,7,8,9,10},1),{11,10,9,8,7,6,5,4,3,2}),11)<2,0,11-MOD(SUMPRODUCT(--MID(SUBSTITUTE(SUBSTITUTE(SUBSTITUTE(SUBSTITUTE(C18,".",""),"-","")," ",""),"/",""),{1,2,3,4,5,6,7,8,9,10},1),{11,10,9,8,7,6,5,4,3,2}),11))),FALSE()),AND(LEN(SUBSTITUTE(SUBSTITUTE(SUBSTITUTE(SUBSTITUTE(C18,".",""),"-","")," ",""),"/",""))=14,ISNUMBER(VALUE(SUBSTITUTE(SUBSTITUTE(SUBSTITUTE(SUBSTITUTE(C18,".",""),"-","")," ",""),"/",""))))),FALSE())),G18>F18),"Revisar",IF(I18<>"Sim","Falta informe","OK")))
E19: =IF(D19="","",IFERROR(VLOOKUP(D19,Listas!$A$5:$B$16,2,FALSE()),"")) | K19: =IF(AND(A19="",B19="",D19="",F19=""),"",IF(OR(A19="",B19="",D19="",F19="",NOT(IFERROR(OR(IFERROR(AND(LEN(SUBSTITUTE(SUBSTITUTE(SUBSTITUTE(SUBSTITUTE(C19,".",""),"-","")," ",""),"/",""))=11,SUBSTITUTE(SUBSTITUTE(SUBSTITUTE(SUBSTITUTE(C19,".",""),"-","")," ",""),"/","")<>REPT(LEFT(SUBSTITUTE(SUBSTITUTE(SUBSTITUTE(SUBSTITUTE(C19,".",""),"-","")," ",""),"/",""),1),11),VALUE(MID(SUBSTITUTE(SUBSTITUTE(SUBSTITUTE(SUBSTITUTE(C19,".",""),"-","")," ",""),"/",""),10,1))=IF(MOD(SUMPRODUCT(--MID(SUBSTITUTE(SUBSTITUTE(SUBSTITUTE(SUBSTITUTE(C19,".",""),"-","")," ",""),"/",""),{1,2,3,4,5,6,7,8,9},1),{10,9,8,7,6,5,4,3,2}),11)<2,0,11-MOD(SUMPRODUCT(--MID(SUBSTITUTE(SUBSTITUTE(SUBSTITUTE(SUBSTITUTE(C19,".",""),"-","")," ",""),"/",""),{1,2,3,4,5,6,7,8,9},1),{10,9,8,7,6,5,4,3,2}),11)),VALUE(MID(SUBSTITUTE(SUBSTITUTE(SUBSTITUTE(SUBSTITUTE(C19,".",""),"-","")," ",""),"/",""),11,1))=IF(MOD(SUMPRODUCT(--MID(SUBSTITUTE(SUBSTITUTE(SUBSTITUTE(SUBSTITUTE(C19,".",""),"-","")," ",""),"/",""),{1,2,3,4,5,6,7,8,9,10},1),{11,10,9,8,7,6,5,4,3,2}),11)<2,0,11-MOD(SUMPRODUCT(--MID(SUBSTITUTE(SUBSTITUTE(SUBSTITUTE(SUBSTITUTE(C19,".",""),"-","")," ",""),"/",""),{1,2,3,4,5,6,7,8,9,10},1),{11,10,9,8,7,6,5,4,3,2}),11))),FALSE()),AND(LEN(SUBSTITUTE(SUBSTITUTE(SUBSTITUTE(SUBSTITUTE(C19,".",""),"-","")," ",""),"/",""))=14,ISNUMBER(VALUE(SUBSTITUTE(SUBSTITUTE(SUBSTITUTE(SUBSTITUTE(C19,".",""),"-","")," ",""),"/",""))))),FALSE())),G19>F19),"Revisar",IF(I19<>"Sim","Falta informe","OK")))
E20: =IF(D20="","",IFERROR(VLOOKUP(D20,Listas!$A$5:$B$16,2,FALSE()),"")) | K20: =IF(AND(A20="",B20="",D20="",F20=""),"",IF(OR(A20="",B20="",D20="",F20="",NOT(IFERROR(OR(IFERROR(AND(LEN(SUBSTITUTE(SUBSTITUTE(SUBSTITUTE(SUBSTITUTE(C20,".",""),"-","")," ",""),"/",""))=11,SUBSTITUTE(SUBSTITUTE(SUBSTITUTE(SUBSTITUTE(C20,".",""),"-","")," ",""),"/","")<>REPT(LEFT(SUBSTITUTE(SUBSTITUTE(SUBSTITUTE(SUBSTITUTE(C20,".",""),"-","")," ",""),"/",""),1),11),VALUE(MID(SUBSTITUTE(SUBSTITUTE(SUBSTITUTE(SUBSTITUTE(C20,".",""),"-","")," ",""),"/",""),10,1))=IF(MOD(SUMPRODUCT(--MID(SUBSTITUTE(SUBSTITUTE(SUBSTITUTE(SUBSTITUTE(C20,".",""),"-","")," ",""),"/",""),{1,2,3,4,5,6,7,8,9},1),{10,9,8,7,6,5,4,3,2}),11)<2,0,11-MOD(SUMPRODUCT(--MID(SUBSTITUTE(SUBSTITUTE(SUBSTITUTE(SUBSTITUTE(C20,".",""),"-","")," ",""),"/",""),{1,2,3,4,5,6,7,8,9},1),{10,9,8,7,6,5,4,3,2}),11)),VALUE(MID(SUBSTITUTE(SUBSTITUTE(SUBSTITUTE(SUBSTITUTE(C20,".",""),"-","")," ",""),"/",""),11,1))=IF(MOD(SUMPRODUCT(--MID(SUBSTITUTE(SUBSTITUTE(SUBSTITUTE(SUBSTITUTE(C20,".",""),"-","")," ",""),"/",""),{1,2,3,4,5,6,7,8,9,10},1),{11,10,9,8,7,6,5,4,3,2}),11)<2,0,11-MOD(SUMPRODUCT(--MID(SUBSTITUTE(SUBSTITUTE(SUBSTITUTE(SUBSTITUTE(C20,".",""),"-","")," ",""),"/",""),{1,2,3,4,5,6,7,8,9,10},1),{11,10,9,8,7,6,5,4,3,2}),11))),FALSE()),AND(LEN(SUBSTITUTE(SUBSTITUTE(SUBSTITUTE(SUBSTITUTE(C20,".",""),"-","")," ",""),"/",""))=14,ISNUMBER(VALUE(SUBSTITUTE(SUBSTITUTE(SUBSTITUTE(SUBSTITUTE(C20,".",""),"-","")," ",""),"/",""))))),FALSE())),G20>F20),"Revisar",IF(I20<>"Sim","Falta informe","OK")))
E21: =IF(D21="","",IFERROR(VLOOKUP(D21,Listas!$A$5:$B$16,2,FALSE()),"")) | K21: =IF(AND(A21="",B21="",D21="",F21=""),"",IF(OR(A21="",B21="",D21="",F21="",NOT(IFERROR(OR(IFERROR(AND(LEN(SUBSTITUTE(SUBSTITUTE(SUBSTITUTE(SUBSTITUTE(C21,".",""),"-","")," ",""),"/",""))=11,SUBSTITUTE(SUBSTITUTE(SUBSTITUTE(SUBSTITUTE(C21,".",""),"-","")," ",""),"/","")<>REPT(LEFT(SUBSTITUTE(SUBSTITUTE(SUBSTITUTE(SUBSTITUTE(C21,".",""),"-","")," ",""),"/",""),1),11),VALUE(MID(SUBSTITUTE(SUBSTITUTE(SUBSTITUTE(SUBSTITUTE(C21,".",""),"-","")," ",""),"/",""),10,1))=IF(MOD(SUMPRODUCT(--MID(SUBSTITUTE(SUBSTITUTE(SUBSTITUTE(SUBSTITUTE(C21,".",""),"-","")," ",""),"/",""),{1,2,3,4,5,6,7,8,9},1),{10,9,8,7,6,5,4,3,2}),11)<2,0,11-MOD(SUMPRODUCT(--MID(SUBSTITUTE(SUBSTITUTE(SUBSTITUTE(SUBSTITUTE(C21,".",""),"-","")," ",""),"/",""),{1,2,3,4,5,6,7,8,9},1),{10,9,8,7,6,5,4,3,2}),11)),VALUE(MID(SUBSTITUTE(SUBSTITUTE(SUBSTITUTE(SUBSTITUTE(C21,".",""),"-","")," ",""),"/",""),11,1))=IF(MOD(SUMPRODUCT(--MID(SUBSTITUTE(SUBSTITUTE(SUBSTITUTE(SUBSTITUTE(C21,".",""),"-","")," ",""),"/",""),{1,2,3,4,5,6,7,8,9,10},1),{11,10,9,8,7,6,5,4,3,2}),11)<2,0,11-MOD(SUMPRODUCT(--MID(SUBSTITUTE(SUBSTITUTE(SUBSTITUTE(SUBSTITUTE(C21,".",""),"-","")," ",""),"/",""),{1,2,3,4,5,6,7,8,9,10},1),{11,10,9,8,7,6,5,4,3,2}),11))),FALSE()),AND(LEN(SUBSTITUTE(SUBSTITUTE(SUBSTITUTE(SUBSTITUTE(C21,".",""),"-","")," ",""),"/",""))=14,ISNUMBER(VALUE(SUBSTITUTE(SUBSTITUTE(SUBSTITUTE(SUBSTITUTE(C21,".",""),"-","")," ",""),"/",""))))),FALSE())),G21>F21),"Revisar",IF(I21<>"Sim","Falta informe","OK")))
... E105: =IF(D105="","",IFERROR(VLOOKUP(D105,Listas!$A$5:$B$16,2,FALSE()),"")) | K105: =IF(AND(A105="",B105="",D105="",F105=""),"",IF(OR(A105="",B105="",D105="",F105="",NOT(IFERROR(OR(IFERROR(AND(LEN(SUBSTITUTE(SUBSTITUTE(SUBSTITUTE(SUBSTITUTE(C105,".",""),"-","")," ",""),"/",""))=11,SUBSTITUTE(SUBSTITUTE(SUBSTITUTE(SUBSTITUTE(C105,".",""),"-","")," ",""),"/","")<>REPT(LEFT(SUBSTITUTE(SUBSTITUTE(SUBSTITUTE(SUBSTITUTE(C105,".",""),"-","")," ",""),"/",""),1),11),VALUE(MID(SUBSTITUTE(SUBSTITUTE(SUBSTITUTE(SUBSTITUTE(C105,".",""),"-","")," ",""),"/",""),10,1))=IF(MOD(SUMPRODUCT(--MID(SUBSTITUTE(SUBSTITUTE(SUBSTITUTE(SUBSTITUTE(C105,".",""),"-","")," ",""),"/",""),{1,2,3,4,5,6,7,8,9},1),{10,9,8,7,6,5,4,3,2}),11)<2,0,11-MOD(SUMPRODUCT(--MID(SUBSTITUTE(SUBSTITUTE(SUBSTITUTE(SUBSTITUTE(C105,".",""),"-","")," ",""),"/",""),{1,2,3,4,5,6,7,8,9},1),{10,9,8,7,6,5,4,3,2}),11)),VALUE(MID(SUBSTITUTE(SUBSTITUTE(SUBSTITUTE(SUBSTITUTE(C105,".",""),"-","")," ",""),"/",""),11,1))=IF(MOD(SUMPRODUCT(--MID(SUBSTITUTE(SUBSTITUTE(SUBSTITUTE(SUBSTITUTE(C105,".",""),"-","")," ",""),"/",""),{1,2,3,4,5,6,7,8,9,10},1),{11,10,9,8,7,6,5,4,3,2}),11)<2,0,11-MOD(SUMPRODUCT(--MID(SUBSTITUTE(SUBSTITUTE(SUBSTITUTE(SUBSTITUTE(C105,".",""),"-","")," ",""),"/",""),{1,2,3,4,5,6,7,8,9,10},1),{11,10,9,8,7,6,5,4,3,2}),11))),FALSE()),AND(LEN(SUBSTITUTE(SUBSTITUTE(SUBSTITUTE(SUBSTITUTE(C105,".",""),"-","")," ",""),"/",""))=14,ISNUMBER(VALUE(SUBSTITUTE(SUBSTITUTE(SUBSTITUTE(SUBSTITUTE(C105,".",""),"-","")," ",""),"/",""))))),FALSE())),G105>F105),"Revisar",IF(I105<>"Sim","Falta informe","OK")))

Sheet Deduções
A1: ◄ Voltar ao Menu
A2: Deduções
A3: Um lançamento por comprovante ou grupo de comprovantes. Educação tem limite por pessoa, saúde não tem limite.
A5: Data | B5: Tipo de dedução | C5: Beneficiário | D5: Prestador ou descrição | E5: CNPJ ou CPF do prestador | F5: Valor (R$) | G5: Comprovante guardado? | H5: Observação | I5: Status
A6: 46091 | B6: Saúde | C6: Fulano de Tal (exemplo) | D6: Clínica Exemplo | E6: 23.456.789/0001-01 | F6: 2400 | G6: Sim | I6: =IF(AND(B6="",F6=""),"",IF(OR(A6="",B6="",C6="",F6="",NOT(IFERROR(OR(IFERROR(AND(LEN(SUBSTITUTE(SUBSTITUTE(SUBSTITUTE(SUBSTITUTE(E6,".",""),"-","")," ",""),"/",""))=11,SUBSTITUTE(SUBSTITUTE(SUBSTITUTE(SUBSTITUTE(E6,".",""),"-","")," ",""),"/","")<>REPT(LEFT(SUBSTITUTE(SUBSTITUTE(SUBSTITUTE(SUBSTITUTE(E6,".",""),"-","")," ",""),"/",""),1),11),VALUE(MID(SUBSTITUTE(SUBSTITUTE(SUBSTITUTE(SUBSTITUTE(E6,".",""),"-","")," ",""),"/",""),10,1))=IF(MOD(SUMPRODUCT(--MID(SUBSTITUTE(SUBSTITUTE(SUBSTITUTE(SUBSTITUTE(E6,".",""),"-","")," ",""),"/",""),{1,2,3,4,5,6,7,8,9},1),{10,9,8,7,6,5,4,3,2}),11)<2,0,11-MOD(SUMPRODUCT(--MID(SUBSTITUTE(SUBSTITUTE(SUBSTITUTE(SUBSTITUTE(E6,".",""),"-","")," ",""),"/",""),{1,2,3,4,5,6,7,8,9},1),{10,9,8,7,6,5,4,3,2}),11)),VALUE(MID(SUBSTITUTE(SUBSTITUTE(SUBSTITUTE(SUBSTITUTE(E6,".",""),"-","")," ",""),"/",""),11,1))=IF(MOD(SUMPRODUCT(--MID(SUBSTITUTE(SUBSTITUTE(SUBSTITUTE(SUBSTITUTE(E6,".",""),"-","")," ",""),"/",""),{1,2,3,4,5,6,7,8,9,10},1),{11,10,9,8,7,6,5,4,3,2}),11)<2,0,11-MOD(SUMPRODUCT(--MID(SUBSTITUTE(SUBSTITUTE(SUBSTITUTE(SUBSTITUTE(E6,".",""),"-","")," ",""),"/",""),{1,2,3,4,5,6,7,8,9,10},1),{11,10,9,8,7,6,5,4,3,2}),11))),FALSE()),AND(LEN(SUBSTITUTE(SUBSTITUTE(SUBSTITUTE(SUBSTITUTE(E6,".",""),"-","")," ",""),"/",""))=14,ISNUMBER(VALUE(SUBSTITUTE(SUBSTITUTE(SUBSTITUTE(SUBSTITUTE(E6,".",""),"-","")," ",""),"/",""))))),FALSE()))),"Revisar",IF(G6<>"Sim","Falta comprovante",IF(AND(B6="Educação",SUMIFS($F$6:$F$155,$B$6:$B$155,"Educação",$C$6:$C$155,C6)>Parâmetros!$B$6),"Acima do limite","OK")))) -> OK
A7: 46178 | B7: Saúde | C7: Filho Exemplo | D7: Dentista Exemplo | E7: 529.982.247-25 | F7: 800 | G7: Sim | I7: =IF(AND(B7="",F7=""),"",IF(OR(A7="",B7="",C7="",F7="",NOT(IFERROR(OR(IFERROR(AND(LEN(SUBSTITUTE(SUBSTITUTE(SUBSTITUTE(SUBSTITUTE(E7,".",""),"-","")," ",""),"/",""))=11,SUBSTITUTE(SUBSTITUTE(SUBSTITUTE(SUBSTITUTE(E7,".",""),"-","")," ",""),"/","")<>REPT(LEFT(SUBSTITUTE(SUBSTITUTE(SUBSTITUTE(SUBSTITUTE(E7,".",""),"-","")," ",""),"/",""),1),11),VALUE(MID(SUBSTITUTE(SUBSTITUTE(SUBSTITUTE(SUBSTITUTE(E7,".",""),"-","")," ",""),"/",""),10,1))=IF(MOD(SUMPRODUCT(--MID(SUBSTITUTE(SUBSTITUTE(SUBSTITUTE(SUBSTITUTE(E7,".",""),"-","")," ",""),"/",""),{1,2,3,4,5,6,7,8,9},1),{10,9,8,7,6,5,4,3,2}),11)<2,0,11-MOD(SUMPRODUCT(--MID(SUBSTITUTE(SUBSTITUTE(SUBSTITUTE(SUBSTITUTE(E7,".",""),"-","")," ",""),"/",""),{1,2,3,4,5,6,7,8,9},1),{10,9,8,7,6,5,4,3,2}),11)),VALUE(MID(SUBSTITUTE(SUBSTITUTE(SUBSTITUTE(SUBSTITUTE(E7,".",""),"-","")," ",""),"/",""),11,1))=IF(MOD(SUMPRODUCT(--MID(SUBSTITUTE(SUBSTITUTE(SUBSTITUTE(SUBSTITUTE(E7,".",""),"-","")," ",""),"/",""),{1,2,3,4,5,6,7,8,9,10},1),{11,10,9,8,7,6,5,4,3,2}),11)<2,0,11-MOD(SUMPRODUCT(--MID(SUBSTITUTE(SUBSTITUTE(SUBSTITUTE(SUBSTITUTE(E7,".",""),"-","")," ",""),"/",""),{1,2,3,4,5,6,7,8,9,10},1),{11,10,9,8,7,6,5,4,3,2}),11))),FALSE()),AND(LEN(SUBSTITUTE(SUBSTITUTE(SUBSTITUTE(SUBSTITUTE(E7,".",""),"-","")," ",""),"/",""))=14,ISNUMBER(VALUE(SUBSTITUTE(SUBSTITUTE(SUBSTITUTE(SUBSTITUTE(E7,".",""),"-","")," ",""),"/",""))))),FALSE()))),"Revisar",IF(G7<>"Sim","Falta comprovante",IF(AND(B7="Educação",SUMIFS($F$6:$F$155,$B$6:$B$155,"Educação",$C$6:$C$155,C7)>Parâmetros!$B$6),"Acima do limite","OK")))) -> OK
A8: 46387 | B8: Educação | C8: Filho Exemplo | D8: Escola Exemplo | E8: 34.567.890/0001-12 | F8: 5200 | G8: Sim | I8: =IF(AND(B8="",F8=""),"",IF(OR(A8="",B8="",C8="",F8="",NOT(IFERROR(OR(IFERROR(AND(LEN(SUBSTITUTE(SUBSTITUTE(SUBSTITUTE(SUBSTITUTE(E8,".",""),"-","")," ",""),"/",""))=11,SUBSTITUTE(SUBSTITUTE(SUBSTITUTE(SUBSTITUTE(E8,".",""),"-","")," ",""),"/","")<>REPT(LEFT(SUBSTITUTE(SUBSTITUTE(SUBSTITUTE(SUBSTITUTE(E8,".",""),"-","")," ",""),"/",""),1),11),VALUE(MID(SUBSTITUTE(SUBSTITUTE(SUBSTITUTE(SUBSTITUTE(E8,".",""),"-","")," ",""),"/",""),10,1))=IF(MOD(SUMPRODUCT(--MID(SUBSTITUTE(SUBSTITUTE(SUBSTITUTE(SUBSTITUTE(E8,".",""),"-","")," ",""),"/",""),{1,2,3,4,5,6,7,8,9},1),{10,9,8,7,6,5,4,3,2}),11)<2,0,11-MOD(SUMPRODUCT(--MID(SUBSTITUTE(SUBSTITUTE(SUBSTITUTE(SUBSTITUTE(E8,".",""),"-","")," ",""),"/",""),{1,2,3,4,5,6,7,8,9},1),{10,9,8,7,6,5,4,3,2}),11)),VALUE(MID(SUBSTITUTE(SUBSTITUTE(SUBSTITUTE(SUBSTITUTE(E8,".",""),"-","")," ",""),"/",""),11,1))=IF(MOD(SUMPRODUCT(--MID(SUBSTITUTE(SUBSTITUTE(SUBSTITUTE(SUBSTITUTE(E8,".",""),"-","")," ",""),"/",""),{1,2,3,4,5,6,7,8,9,10},1),{11,10,9,8,7,6,5,4,3,2}),11)<2,0,11-MOD(SUMPRODUCT(--MID(SUBSTITUTE(SUBSTITUTE(SUBSTITUTE(SUBSTITUTE(E8,".",""),"-","")," ",""),"/",""),{1,2,3,4,5,6,7,8,9,10},1),{11,10,9,8,7,6,5,4,3,2}),11))),FALSE()),AND(LEN(SUBSTITUTE(SUBSTITUTE(SUBSTITUTE(SUBSTITUTE(E8,".",""),"-","")," ",""),"/",""))=14,ISNUMBER(VALUE(SUBSTITUTE(SUBSTITUTE(SUBSTITUTE(SUBSTITUTE(E8,".",""),"-","")," ",""),"/",""))))),FALSE()))),"Revisar",IF(G8<>"Sim","Falta comprovante",IF(AND(B8="Educação",SUMIFS($F$6:$F$155,$B$6:$B$155,"Educação",$C$6:$C$155,C8)>Parâmetros!$B$6),"Acima do limite","OK")))) -> Acima do limite
A9: 46387 | B9: Previdência privada (PGBL) | C9: Fulano de Tal (exemplo) | D9: Previdência Exemplo | E9: 45.678.901/0001-23 | F9: 3000 | G9: Não | I9: =IF(AND(B9="",F9=""),"",IF(OR(A9="",B9="",C9="",F9="",NOT(IFERROR(OR(IFERROR(AND(LEN(SUBSTITUTE(SUBSTITUTE(SUBSTITUTE(SUBSTITUTE(E9,".",""),"-","")," ",""),"/",""))=11,SUBSTITUTE(SUBSTITUTE(SUBSTITUTE(SUBSTITUTE(E9,".",""),"-","")," ",""),"/","")<>REPT(LEFT(SUBSTITUTE(SUBSTITUTE(SUBSTITUTE(SUBSTITUTE(E9,".",""),"-","")," ",""),"/",""),1),11),VALUE(MID(SUBSTITUTE(SUBSTITUTE(SUBSTITUTE(SUBSTITUTE(E9,".",""),"-","")," ",""),"/",""),10,1))=IF(MOD(SUMPRODUCT(--MID(SUBSTITUTE(SUBSTITUTE(SUBSTITUTE(SUBSTITUTE(E9,".",""),"-","")," ",""),"/",""),{1,2,3,4,5,6,7,8,9},1),{10,9,8,7,6,5,4,3,2}),11)<2,0,11-MOD(SUMPRODUCT(--MID(SUBSTITUTE(SUBSTITUTE(SUBSTITUTE(SUBSTITUTE(E9,".",""),"-","")," ",""),"/",""),{1,2,3,4,5,6,7,8,9},1),{10,9,8,7,6,5,4,3,2}),11)),VALUE(MID(SUBSTITUTE(SUBSTITUTE(SUBSTITUTE(SUBSTITUTE(E9,".",""),"-","")," ",""),"/",""),11,1))=IF(MOD(SUMPRODUCT(--MID(SUBSTITUTE(SUBSTITUTE(SUBSTITUTE(SUBSTITUTE(E9,".",""),"-","")," ",""),"/",""),{1,2,3,4,5,6,7,8,9,10},1),{11,10,9,8,7,6,5,4,3,2}),11)<2,0,11-MOD(SUMPRODUCT(--MID(SUBSTITUTE(SUBSTITUTE(SUBSTITUTE(SUBSTITUTE(E9,".",""),"-","")," ",""),"/",""),{1,2,3,4,5,6,7,8,9,10},1),{11,10,9,8,7,6,5,4,3,2}),11))),FALSE()),AND(LEN(SUBSTITUTE(SUBSTITUTE(SUBSTITUTE(SUBSTITUTE(E9,".",""),"-","")," ",""),"/",""))=14,ISNUMBER(VALUE(SUBSTITUTE(SUBSTITUTE(SUBSTITUTE(SUBSTITUTE(E9,".",""),"-","")," ",""),"/",""))))),FALSE()))),"Revisar",IF(G9<>"Sim","Falta comprovante",IF(AND(B9="Educação",SUMIFS($F$6:$F$155,$B$6:$B$155,"Educação",$C$6:$C$155,C9)>Parâmetros!$B$6),"Acima do limite","OK")))) -> Falta comprovante
I10: =IF(AND(B10="",F10=""),"",IF(OR(A10="",B10="",C10="",F10="",NOT(IFERROR(OR(IFERROR(AND(LEN(SUBSTITUTE(SUBSTITUTE(SUBSTITUTE(SUBSTITUTE(E10,".",""),"-","")," ",""),"/",""))=11,SUBSTITUTE(SUBSTITUTE(SUBSTITUTE(SUBSTITUTE(E10,".",""),"-","")," ",""),"/","")<>REPT(LEFT(SUBSTITUTE(SUBSTITUTE(SUBSTITUTE(SUBSTITUTE(E10,".",""),"-","")," ",""),"/",""),1),11),VALUE(MID(SUBSTITUTE(SUBSTITUTE(SUBSTITUTE(SUBSTITUTE(E10,".",""),"-","")," ",""),"/",""),10,1))=IF(MOD(SUMPRODUCT(--MID(SUBSTITUTE(SUBSTITUTE(SUBSTITUTE(SUBSTITUTE(E10,".",""),"-","")," ",""),"/",""),{1,2,3,4,5,6,7,8,9},1),{10,9,8,7,6,5,4,3,2}),11)<2,0,11-MOD(SUMPRODUCT(--MID(SUBSTITUTE(SUBSTITUTE(SUBSTITUTE(SUBSTITUTE(E10,".",""),"-","")," ",""),"/",""),{1,2,3,4,5,6,7,8,9},1),{10,9,8,7,6,5,4,3,2}),11)),VALUE(MID(SUBSTITUTE(SUBSTITUTE(SUBSTITUTE(SUBSTITUTE(E10,".",""),"-","")," ",""),"/",""),11,1))=IF(MOD(SUMPRODUCT(--MID(SUBSTITUTE(SUBSTITUTE(SUBSTITUTE(SUBSTITUTE(E10,".",""),"-","")," ",""),"/",""),{1,2,3,4,5,6,7,8,9,10},1),{11,10,9,8,7,6,5,4,3,2}),11)<2,0,11-MOD(SUMPRODUCT(--MID(SUBSTITUTE(SUBSTITUTE(SUBSTITUTE(SUBSTITUTE(E10,".",""),"-","")," ",""),"/",""),{1,2,3,4,5,6,7,8,9,10},1),{11,10,9,8,7,6,5,4,3,2}),11))),FALSE()),AND(LEN(SUBSTITUTE(SUBSTITUTE(SUBSTITUTE(SUBSTITUTE(E10,".",""),"-","")," ",""),"/",""))=14,ISNUMBER(VALUE(SUBSTITUTE(SUBSTITUTE(SUBSTITUTE(SUBSTITUTE(E10,".",""),"-","")," ",""),"/",""))))),FALSE()))),"Revisar",IF(G10<>"Sim","Falta comprovante",IF(AND(B10="Educação",SUMIFS($F$6:$F$155,$B$6:$B$155,"Educação",$C$6:$C$155,C10)>Parâmetros!$B$6),"Acima do limite","OK"))))
I11: =IF(AND(B11="",F11=""),"",IF(OR(A11="",B11="",C11="",F11="",NOT(IFERROR(OR(IFERROR(AND(LEN(SUBSTITUTE(SUBSTITUTE(SUBSTITUTE(SUBSTITUTE(E11,".",""),"-","")," ",""),"/",""))=11,SUBSTITUTE(SUBSTITUTE(SUBSTITUTE(SUBSTITUTE(E11,".",""),"-","")," ",""),"/","")<>REPT(LEFT(SUBSTITUTE(SUBSTITUTE(SUBSTITUTE(SUBSTITUTE(E11,".",""),"-","")," ",""),"/",""),1),11),VALUE(MID(SUBSTITUTE(SUBSTITUTE(SUBSTITUTE(SUBSTITUTE(E11,".",""),"-","")," ",""),"/",""),10,1))=IF(MOD(SUMPRODUCT(--MID(SUBSTITUTE(SUBSTITUTE(SUBSTITUTE(SUBSTITUTE(E11,".",""),"-","")," ",""),"/",""),{1,2,3,4,5,6,7,8,9},1),{10,9,8,7,6,5,4,3,2}),11)<2,0,11-MOD(SUMPRODUCT(--MID(SUBSTITUTE(SUBSTITUTE(SUBSTITUTE(SUBSTITUTE(E11,".",""),"-","")," ",""),"/",""),{1,2,3,4,5,6,7,8,9},1),{10,9,8,7,6,5,4,3,2}),11)),VALUE(MID(SUBSTITUTE(SUBSTITUTE(SUBSTITUTE(SUBSTITUTE(E11,".",""),"-","")," ",""),"/",""),11,1))=IF(MOD(SUMPRODUCT(--MID(SUBSTITUTE(SUBSTITUTE(SUBSTITUTE(SUBSTITUTE(E11,".",""),"-","")," ",""),"/",""),{1,2,3,4,5,6,7,8,9,10},1),{11,10,9,8,7,6,5,4,3,2}),11)<2,0,11-MOD(SUMPRODUCT(--MID(SUBSTITUTE(SUBSTITUTE(SUBSTITUTE(SUBSTITUTE(E11,".",""),"-","")," ",""),"/",""),{1,2,3,4,5,6,7,8,9,10},1),{11,10,9,8,7,6,5,4,3,2}),11))),FALSE()),AND(LEN(SUBSTITUTE(SUBSTITUTE(SUBSTITUTE(SUBSTITUTE(E11,".",""),"-","")," ",""),"/",""))=14,ISNUMBER(VALUE(SUBSTITUTE(SUBSTITUTE(SUBSTITUTE(SUBSTITUTE(E11,".",""),"-","")," ",""),"/",""))))),FALSE()))),"Revisar",IF(G11<>"Sim","Falta comprovante",IF(AND(B11="Educação",SUMIFS($F$6:$F$155,$B$6:$B$155,"Educação",$C$6:$C$155,C11)>Parâmetros!$B$6),"Acima do limite","OK"))))
I12: =IF(AND(B12="",F12=""),"",IF(OR(A12="",B12="",C12="",F12="",NOT(IFERROR(OR(IFERROR(AND(LEN(SUBSTITUTE(SUBSTITUTE(SUBSTITUTE(SUBSTITUTE(E12,".",""),"-","")," ",""),"/",""))=11,SUBSTITUTE(SUBSTITUTE(SUBSTITUTE(SUBSTITUTE(E12,".",""),"-","")," ",""),"/","")<>REPT(LEFT(SUBSTITUTE(SUBSTITUTE(SUBSTITUTE(SUBSTITUTE(E12,".",""),"-","")," ",""),"/",""),1),11),VALUE(MID(SUBSTITUTE(SUBSTITUTE(SUBSTITUTE(SUBSTITUTE(E12,".",""),"-","")," ",""),"/",""),10,1))=IF(MOD(SUMPRODUCT(--MID(SUBSTITUTE(SUBSTITUTE(SUBSTITUTE(SUBSTITUTE(E12,".",""),"-","")," ",""),"/",""),{1,2,3,4,5,6,7,8,9},1),{10,9,8,7,6,5,4,3,2}),11)<2,0,11-MOD(SUMPRODUCT(--MID(SUBSTITUTE(SUBSTITUTE(SUBSTITUTE(SUBSTITUTE(E12,".",""),"-","")," ",""),"/",""),{1,2,3,4,5,6,7,8,9},1),{10,9,8,7,6,5,4,3,2}),11)),VALUE(MID(SUBSTITUTE(SUBSTITUTE(SUBSTITUTE(SUBSTITUTE(E12,".",""),"-","")," ",""),"/",""),11,1))=IF(MOD(SUMPRODUCT(--MID(SUBSTITUTE(SUBSTITUTE(SUBSTITUTE(SUBSTITUTE(E12,".",""),"-","")," ",""),"/",""),{1,2,3,4,5,6,7,8,9,10},1),{11,10,9,8,7,6,5,4,3,2}),11)<2,0,11-MOD(SUMPRODUCT(--MID(SUBSTITUTE(SUBSTITUTE(SUBSTITUTE(SUBSTITUTE(E12,".",""),"-","")," ",""),"/",""),{1,2,3,4,5,6,7,8,9,10},1),{11,10,9,8,7,6,5,4,3,2}),11))),FALSE()),AND(LEN(SUBSTITUTE(SUBSTITUTE(SUBSTITUTE(SUBSTITUTE(E12,".",""),"-","")," ",""),"/",""))=14,ISNUMBER(VALUE(SUBSTITUTE(SUBSTITUTE(SUBSTITUTE(SUBSTITUTE(E12,".",""),"-","")," ",""),"/",""))))),FALSE()))),"Revisar",IF(G12<>"Sim","Falta comprovante",IF(AND(B12="Educação",SUMIFS($F$6:$F$155,$B$6:$B$155,"Educação",$C$6:$C$155,C12)>Parâmetros!$B$6),"Acima do limite","OK"))))
I13: =IF(AND(B13="",F13=""),"",IF(OR(A13="",B13="",C13="",F13="",NOT(IFERROR(OR(IFERROR(AND(LEN(SUBSTITUTE(SUBSTITUTE(SUBSTITUTE(SUBSTITUTE(E13,".",""),"-","")," ",""),"/",""))=11,SUBSTITUTE(SUBSTITUTE(SUBSTITUTE(SUBSTITUTE(E13,".",""),"-","")," ",""),"/","")<>REPT(LEFT(SUBSTITUTE(SUBSTITUTE(SUBSTITUTE(SUBSTITUTE(E13,".",""),"-","")," ",""),"/",""),1),11),VALUE(MID(SUBSTITUTE(SUBSTITUTE(SUBSTITUTE(SUBSTITUTE(E13,".",""),"-","")," ",""),"/",""),10,1))=IF(MOD(SUMPRODUCT(--MID(SUBSTITUTE(SUBSTITUTE(SUBSTITUTE(SUBSTITUTE(E13,".",""),"-","")," ",""),"/",""),{1,2,3,4,5,6,7,8,9},1),{10,9,8,7,6,5,4,3,2}),11)<2,0,11-MOD(SUMPRODUCT(--MID(SUBSTITUTE(SUBSTITUTE(SUBSTITUTE(SUBSTITUTE(E13,".",""),"-","")," ",""),"/",""),{1,2,3,4,5,6,7,8,9},1),{10,9,8,7,6,5,4,3,2}),11)),VALUE(MID(SUBSTITUTE(SUBSTITUTE(SUBSTITUTE(SUBSTITUTE(E13,".",""),"-","")," ",""),"/",""),11,1))=IF(MOD(SUMPRODUCT(--MID(SUBSTITUTE(SUBSTITUTE(SUBSTITUTE(SUBSTITUTE(E13,".",""),"-","")," ",""),"/",""),{1,2,3,4,5,6,7,8,9,10},1),{11,10,9,8,7,6,5,4,3,2}),11)<2,0,11-MOD(SUMPRODUCT(--MID(SUBSTITUTE(SUBSTITUTE(SUBSTITUTE(SUBSTITUTE(E13,".",""),"-","")," ",""),"/",""),{1,2,3,4,5,6,7,8,9,10},1),{11,10,9,8,7,6,5,4,3,2}),11))),FALSE()),AND(LEN(SUBSTITUTE(SUBSTITUTE(SUBSTITUTE(SUBSTITUTE(E13,".",""),"-","")," ",""),"/",""))=14,ISNUMBER(VALUE(SUBSTITUTE(SUBSTITUTE(SUBSTITUTE(SUBSTITUTE(E13,".",""),"-","")," ",""),"/",""))))),FALSE()))),"Revisar",IF(G13<>"Sim","Falta comprovante",IF(AND(B13="Educação",SUMIFS($F$6:$F$155,$B$6:$B$155,"Educação",$C$6:$C$155,C13)>Parâmetros!$B$6),"Acima do limite","OK"))))
I14: =IF(AND(B14="",F14=""),"",IF(OR(A14="",B14="",C14="",F14="",NOT(IFERROR(OR(IFERROR(AND(LEN(SUBSTITUTE(SUBSTITUTE(SUBSTITUTE(SUBSTITUTE(E14,".",""),"-","")," ",""),"/",""))=11,SUBSTITUTE(SUBSTITUTE(SUBSTITUTE(SUBSTITUTE(E14,".",""),"-","")," ",""),"/","")<>REPT(LEFT(SUBSTITUTE(SUBSTITUTE(SUBSTITUTE(SUBSTITUTE(E14,".",""),"-","")," ",""),"/",""),1),11),VALUE(MID(SUBSTITUTE(SUBSTITUTE(SUBSTITUTE(SUBSTITUTE(E14,".",""),"-","")," ",""),"/",""),10,1))=IF(MOD(SUMPRODUCT(--MID(SUBSTITUTE(SUBSTITUTE(SUBSTITUTE(SUBSTITUTE(E14,".",""),"-","")," ",""),"/",""),{1,2,3,4,5,6,7,8,9},1),{10,9,8,7,6,5,4,3,2}),11)<2,0,11-MOD(SUMPRODUCT(--MID(SUBSTITUTE(SUBSTITUTE(SUBSTITUTE(SUBSTITUTE(E14,".",""),"-","")," ",""),"/",""),{1,2,3,4,5,6,7,8,9},1),{10,9,8,7,6,5,4,3,2}),11)),VALUE(MID(SUBSTITUTE(SUBSTITUTE(SUBSTITUTE(SUBSTITUTE(E14,".",""),"-","")," ",""),"/",""),11,1))=IF(MOD(SUMPRODUCT(--MID(SUBSTITUTE(SUBSTITUTE(SUBSTITUTE(SUBSTITUTE(E14,".",""),"-","")," ",""),"/",""),{1,2,3,4,5,6,7,8,9,10},1),{11,10,9,8,7,6,5,4,3,2}),11)<2,0,11-MOD(SUMPRODUCT(--MID(SUBSTITUTE(SUBSTITUTE(SUBSTITUTE(SUBSTITUTE(E14,".",""),"-","")," ",""),"/",""),{1,2,3,4,5,6,7,8,9,10},1),{11,10,9,8,7,6,5,4,3,2}),11))),FALSE()),AND(LEN(SUBSTITUTE(SUBSTITUTE(SUBSTITUTE(SUBSTITUTE(E14,".",""),"-","")," ",""),"/",""))=14,ISNUMBER(VALUE(SUBSTITUTE(SUBSTITUTE(SUBSTITUTE(SUBSTITUTE(E14,".",""),"-","")," ",""),"/",""))))),FALSE()))),"Revisar",IF(G14<>"Sim","Falta comprovante",IF(AND(B14="Educação",SUMIFS($F$6:$F$155,$B$6:$B$155,"Educação",$C$6:$C$155,C14)>Parâmetros!$B$6),"Acima do limite","OK"))))
I15: =IF(AND(B15="",F15=""),"",IF(OR(A15="",B15="",C15="",F15="",NOT(IFERROR(OR(IFERROR(AND(LEN(SUBSTITUTE(SUBSTITUTE(SUBSTITUTE(SUBSTITUTE(E15,".",""),"-","")," ",""),"/",""))=11,SUBSTITUTE(SUBSTITUTE(SUBSTITUTE(SUBSTITUTE(E15,".",""),"-","")," ",""),"/","")<>REPT(LEFT(SUBSTITUTE(SUBSTITUTE(SUBSTITUTE(SUBSTITUTE(E15,".",""),"-","")," ",""),"/",""),1),11),VALUE(MID(SUBSTITUTE(SUBSTITUTE(SUBSTITUTE(SUBSTITUTE(E15,".",""),"-","")," ",""),"/",""),10,1))=IF(MOD(SUMPRODUCT(--MID(SUBSTITUTE(SUBSTITUTE(SUBSTITUTE(SUBSTITUTE(E15,".",""),"-","")," ",""),"/",""),{1,2,3,4,5,6,7,8,9},1),{10,9,8,7,6,5,4,3,2}),11)<2,0,11-MOD(SUMPRODUCT(--MID(SUBSTITUTE(SUBSTITUTE(SUBSTITUTE(SUBSTITUTE(E15,".",""),"-","")," ",""),"/",""),{1,2,3,4,5,6,7,8,9},1),{10,9,8,7,6,5,4,3,2}),11)),VALUE(MID(SUBSTITUTE(SUBSTITUTE(SUBSTITUTE(SUBSTITUTE(E15,".",""),"-","")," ",""),"/",""),11,1))=IF(MOD(SUMPRODUCT(--MID(SUBSTITUTE(SUBSTITUTE(SUBSTITUTE(SUBSTITUTE(E15,".",""),"-","")," ",""),"/",""),{1,2,3,4,5,6,7,8,9,10},1),{11,10,9,8,7,6,5,4,3,2}),11)<2,0,11-MOD(SUMPRODUCT(--MID(SUBSTITUTE(SUBSTITUTE(SUBSTITUTE(SUBSTITUTE(E15,".",""),"-","")," ",""),"/",""),{1,2,3,4,5,6,7,8,9,10},1),{11,10,9,8,7,6,5,4,3,2}),11))),FALSE()),AND(LEN(SUBSTITUTE(SUBSTITUTE(SUBSTITUTE(SUBSTITUTE(E15,".",""),"-","")," ",""),"/",""))=14,ISNUMBER(VALUE(SUBSTITUTE(SUBSTITUTE(SUBSTITUTE(SUBSTITUTE(E15,".",""),"-","")," ",""),"/",""))))),FALSE()))),"Revisar",IF(G15<>"Sim","Falta comprovante",IF(AND(B15="Educação",SUMIFS($F$6:$F$155,$B$6:$B$155,"Educação",$C$6:$C$155,C15)>Parâmetros!$B$6),"Acima do limite","OK"))))
I16: =IF(AND(B16="",F16=""),"",IF(OR(A16="",B16="",C16="",F16="",NOT(IFERROR(OR(IFERROR(AND(LEN(SUBSTITUTE(SUBSTITUTE(SUBSTITUTE(SUBSTITUTE(E16,".",""),"-","")," ",""),"/",""))=11,SUBSTITUTE(SUBSTITUTE(SUBSTITUTE(SUBSTITUTE(E16,".",""),"-","")," ",""),"/","")<>REPT(LEFT(SUBSTITUTE(SUBSTITUTE(SUBSTITUTE(SUBSTITUTE(E16,".",""),"-","")," ",""),"/",""),1),11),VALUE(MID(SUBSTITUTE(SUBSTITUTE(SUBSTITUTE(SUBSTITUTE(E16,".",""),"-","")," ",""),"/",""),10,1))=IF(MOD(SUMPRODUCT(--MID(SUBSTITUTE(SUBSTITUTE(SUBSTITUTE(SUBSTITUTE(E16,".",""),"-","")," ",""),"/",""),{1,2,3,4,5,6,7,8,9},1),{10,9,8,7,6,5,4,3,2}),11)<2,0,11-MOD(SUMPRODUCT(--MID(SUBSTITUTE(SUBSTITUTE(SUBSTITUTE(SUBSTITUTE(E16,".",""),"-","")," ",""),"/",""),{1,2,3,4,5,6,7,8,9},1),{10,9,8,7,6,5,4,3,2}),11)),VALUE(MID(SUBSTITUTE(SUBSTITUTE(SUBSTITUTE(SUBSTITUTE(E16,".",""),"-","")," ",""),"/",""),11,1))=IF(MOD(SUMPRODUCT(--MID(SUBSTITUTE(SUBSTITUTE(SUBSTITUTE(SUBSTITUTE(E16,".",""),"-","")," ",""),"/",""),{1,2,3,4,5,6,7,8,9,10},1),{11,10,9,8,7,6,5,4,3,2}),11)<2,0,11-MOD(SUMPRODUCT(--MID(SUBSTITUTE(SUBSTITUTE(SUBSTITUTE(SUBSTITUTE(E16,".",""),"-","")," ",""),"/",""),{1,2,3,4,5,6,7,8,9,10},1),{11,10,9,8,7,6,5,4,3,2}),11))),FALSE()),AND(LEN(SUBSTITUTE(SUBSTITUTE(SUBSTITUTE(SUBSTITUTE(E16,".",""),"-","")," ",""),"/",""))=14,ISNUMBER(VALUE(SUBSTITUTE(SUBSTITUTE(SUBSTITUTE(SUBSTITUTE(E16,".",""),"-","")," ",""),"/",""))))),FALSE()))),"Revisar",IF(G16<>"Sim","Falta comprovante",IF(AND(B16="Educação",SUMIFS($F$6:$F$155,$B$6:$B$155,"Educação",$C$6:$C$155,C16)>Parâmetros!$B$6),"Acima do limite","OK"))))
I17: =IF(AND(B17="",F17=""),"",IF(OR(A17="",B17="",C17="",F17="",NOT(IFERROR(OR(IFERROR(AND(LEN(SUBSTITUTE(SUBSTITUTE(SUBSTITUTE(SUBSTITUTE(E17,".",""),"-","")," ",""),"/",""))=11,SUBSTITUTE(SUBSTITUTE(SUBSTITUTE(SUBSTITUTE(E17,".",""),"-","")," ",""),"/","")<>REPT(LEFT(SUBSTITUTE(SUBSTITUTE(SUBSTITUTE(SUBSTITUTE(E17,".",""),"-","")," ",""),"/",""),1),11),VALUE(MID(SUBSTITUTE(SUBSTITUTE(SUBSTITUTE(SUBSTITUTE(E17,".",""),"-","")," ",""),"/",""),10,1))=IF(MOD(SUMPRODUCT(--MID(SUBSTITUTE(SUBSTITUTE(SUBSTITUTE(SUBSTITUTE(E17,".",""),"-","")," ",""),"/",""),{1,2,3,4,5,6,7,8,9},1),{10,9,8,7,6,5,4,3,2}),11)<2,0,11-MOD(SUMPRODUCT(--MID(SUBSTITUTE(SUBSTITUTE(SUBSTITUTE(SUBSTITUTE(E17,".",""),"-","")," ",""),"/",""),{1,2,3,4,5,6,7,8,9},1),{10,9,8,7,6,5,4,3,2}),11)),VALUE(MID(SUBSTITUTE(SUBSTITUTE(SUBSTITUTE(SUBSTITUTE(E17,".",""),"-","")," ",""),"/",""),11,1))=IF(MOD(SUMPRODUCT(--MID(SUBSTITUTE(SUBSTITUTE(SUBSTITUTE(SUBSTITUTE(E17,".",""),"-","")," ",""),"/",""),{1,2,3,4,5,6,7,8,9,10},1),{11,10,9,8,7,6,5,4,3,2}),11)<2,0,11-MOD(SUMPRODUCT(--MID(SUBSTITUTE(SUBSTITUTE(SUBSTITUTE(SUBSTITUTE(E17,".",""),"-","")," ",""),"/",""),{1,2,3,4,5,6,7,8,9,10},1),{11,10,9,8,7,6,5,4,3,2}),11))),FALSE()),AND(LEN(SUBSTITUTE(SUBSTITUTE(SUBSTITUTE(SUBSTITUTE(E17,".",""),"-","")," ",""),"/",""))=14,ISNUMBER(VALUE(SUBSTITUTE(SUBSTITUTE(SUBSTITUTE(SUBSTITUTE(E17,".",""),"-","")," ",""),"/",""))))),FALSE()))),"Revisar",IF(G17<>"Sim","Falta comprovante",IF(AND(B17="Educação",SUMIFS($F$6:$F$155,$B$6:$B$155,"Educação",$C$6:$C$155,C17)>Parâmetros!$B$6),"Acima do limite","OK"))))
I18: =IF(AND(B18="",F18=""),"",IF(OR(A18="",B18="",C18="",F18="",NOT(IFERROR(OR(IFERROR(AND(LEN(SUBSTITUTE(SUBSTITUTE(SUBSTITUTE(SUBSTITUTE(E18,".",""),"-","")," ",""),"/",""))=11,SUBSTITUTE(SUBSTITUTE(SUBSTITUTE(SUBSTITUTE(E18,".",""),"-","")," ",""),"/","")<>REPT(LEFT(SUBSTITUTE(SUBSTITUTE(SUBSTITUTE(SUBSTITUTE(E18,".",""),"-","")," ",""),"/",""),1),11),VALUE(MID(SUBSTITUTE(SUBSTITUTE(SUBSTITUTE(SUBSTITUTE(E18,".",""),"-","")," ",""),"/",""),10,1))=IF(MOD(SUMPRODUCT(--MID(SUBSTITUTE(SUBSTITUTE(SUBSTITUTE(SUBSTITUTE(E18,".",""),"-","")," ",""),"/",""),{1,2,3,4,5,6,7,8,9},1),{10,9,8,7,6,5,4,3,2}),11)<2,0,11-MOD(SUMPRODUCT(--MID(SUBSTITUTE(SUBSTITUTE(SUBSTITUTE(SUBSTITUTE(E18,".",""),"-","")," ",""),"/",""),{1,2,3,4,5,6,7,8,9},1),{10,9,8,7,6,5,4,3,2}),11)),VALUE(MID(SUBSTITUTE(SUBSTITUTE(SUBSTITUTE(SUBSTITUTE(E18,".",""),"-","")," ",""),"/",""),11,1))=IF(MOD(SUMPRODUCT(--MID(SUBSTITUTE(SUBSTITUTE(SUBSTITUTE(SUBSTITUTE(E18,".",""),"-","")," ",""),"/",""),{1,2,3,4,5,6,7,8,9,10},1),{11,10,9,8,7,6,5,4,3,2}),11)<2,0,11-MOD(SUMPRODUCT(--MID(SUBSTITUTE(SUBSTITUTE(SUBSTITUTE(SUBSTITUTE(E18,".",""),"-","")," ",""),"/",""),{1,2,3,4,5,6,7,8,9,10},1),{11,10,9,8,7,6,5,4,3,2}),11))),FALSE()),AND(LEN(SUBSTITUTE(SUBSTITUTE(SUBSTITUTE(SUBSTITUTE(E18,".",""),"-","")," ",""),"/",""))=14,ISNUMBER(VALUE(SUBSTITUTE(SUBSTITUTE(SUBSTITUTE(SUBSTITUTE(E18,".",""),"-","")," ",""),"/",""))))),FALSE()))),"Revisar",IF(G18<>"Sim","Falta comprovante",IF(AND(B18="Educação",SUMIFS($F$6:$F$155,$B$6:$B$155,"Educação",$C$6:$C$155,C18)>Parâmetros!$B$6),"Acima do limite","OK"))))
I19: =IF(AND(B19="",F19=""),"",IF(OR(A19="",B19="",C19="",F19="",NOT(IFERROR(OR(IFERROR(AND(LEN(SUBSTITUTE(SUBSTITUTE(SUBSTITUTE(SUBSTITUTE(E19,".",""),"-","")," ",""),"/",""))=11,SUBSTITUTE(SUBSTITUTE(SUBSTITUTE(SUBSTITUTE(E19,".",""),"-","")," ",""),"/","")<>REPT(LEFT(SUBSTITUTE(SUBSTITUTE(SUBSTITUTE(SUBSTITUTE(E19,".",""),"-","")," ",""),"/",""),1),11),VALUE(MID(SUBSTITUTE(SUBSTITUTE(SUBSTITUTE(SUBSTITUTE(E19,".",""),"-","")," ",""),"/",""),10,1))=IF(MOD(SUMPRODUCT(--MID(SUBSTITUTE(SUBSTITUTE(SUBSTITUTE(SUBSTITUTE(E19,".",""),"-","")," ",""),"/",""),{1,2,3,4,5,6,7,8,9},1),{10,9,8,7,6,5,4,3,2}),11)<2,0,11-MOD(SUMPRODUCT(--MID(SUBSTITUTE(SUBSTITUTE(SUBSTITUTE(SUBSTITUTE(E19,".",""),"-","")," ",""),"/",""),{1,2,3,4,5,6,7,8,9},1),{10,9,8,7,6,5,4,3,2}),11)),VALUE(MID(SUBSTITUTE(SUBSTITUTE(SUBSTITUTE(SUBSTITUTE(E19,".",""),"-","")," ",""),"/",""),11,1))=IF(MOD(SUMPRODUCT(--MID(SUBSTITUTE(SUBSTITUTE(SUBSTITUTE(SUBSTITUTE(E19,".",""),"-","")," ",""),"/",""),{1,2,3,4,5,6,7,8,9,10},1),{11,10,9,8,7,6,5,4,3,2}),11)<2,0,11-MOD(SUMPRODUCT(--MID(SUBSTITUTE(SUBSTITUTE(SUBSTITUTE(SUBSTITUTE(E19,".",""),"-","")," ",""),"/",""),{1,2,3,4,5,6,7,8,9,10},1),{11,10,9,8,7,6,5,4,3,2}),11))),FALSE()),AND(LEN(SUBSTITUTE(SUBSTITUTE(SUBSTITUTE(SUBSTITUTE(E19,".",""),"-","")," ",""),"/",""))=14,ISNUMBER(VALUE(SUBSTITUTE(SUBSTITUTE(SUBSTITUTE(SUBSTITUTE(E19,".",""),"-","")," ",""),"/",""))))),FALSE()))),"Revisar",IF(G19<>"Sim","Falta comprovante",IF(AND(B19="Educação",SUMIFS($F$6:$F$155,$B$6:$B$155,"Educação",$C$6:$C$155,C19)>Parâmetros!$B$6),"Acima do limite","OK"))))
I20: =IF(AND(B20="",F20=""),"",IF(OR(A20="",B20="",C20="",F20="",NOT(IFERROR(OR(IFERROR(AND(LEN(SUBSTITUTE(SUBSTITUTE(SUBSTITUTE(SUBSTITUTE(E20,".",""),"-","")," ",""),"/",""))=11,SUBSTITUTE(SUBSTITUTE(SUBSTITUTE(SUBSTITUTE(E20,".",""),"-","")," ",""),"/","")<>REPT(LEFT(SUBSTITUTE(SUBSTITUTE(SUBSTITUTE(SUBSTITUTE(E20,".",""),"-","")," ",""),"/",""),1),11),VALUE(MID(SUBSTITUTE(SUBSTITUTE(SUBSTITUTE(SUBSTITUTE(E20,".",""),"-","")," ",""),"/",""),10,1))=IF(MOD(SUMPRODUCT(--MID(SUBSTITUTE(SUBSTITUTE(SUBSTITUTE(SUBSTITUTE(E20,".",""),"-","")," ",""),"/",""),{1,2,3,4,5,6,7,8,9},1),{10,9,8,7,6,5,4,3,2}),11)<2,0,11-MOD(SUMPRODUCT(--MID(SUBSTITUTE(SUBSTITUTE(SUBSTITUTE(SUBSTITUTE(E20,".",""),"-","")," ",""),"/",""),{1,2,3,4,5,6,7,8,9},1),{10,9,8,7,6,5,4,3,2}),11)),VALUE(MID(SUBSTITUTE(SUBSTITUTE(SUBSTITUTE(SUBSTITUTE(E20,".",""),"-","")," ",""),"/",""),11,1))=IF(MOD(SUMPRODUCT(--MID(SUBSTITUTE(SUBSTITUTE(SUBSTITUTE(SUBSTITUTE(E20,".",""),"-","")," ",""),"/",""),{1,2,3,4,5,6,7,8,9,10},1),{11,10,9,8,7,6,5,4,3,2}),11)<2,0,11-MOD(SUMPRODUCT(--MID(SUBSTITUTE(SUBSTITUTE(SUBSTITUTE(SUBSTITUTE(E20,".",""),"-","")," ",""),"/",""),{1,2,3,4,5,6,7,8,9,10},1),{11,10,9,8,7,6,5,4,3,2}),11))),FALSE()),AND(LEN(SUBSTITUTE(SUBSTITUTE(SUBSTITUTE(SUBSTITUTE(E20,".",""),"-","")," ",""),"/",""))=14,ISNUMBER(VALUE(SUBSTITUTE(SUBSTITUTE(SUBSTITUTE(SUBSTITUTE(E20,".",""),"-","")," ",""),"/",""))))),FALSE()))),"Revisar",IF(G20<>"Sim","Falta comprovante",IF(AND(B20="Educação",SUMIFS($F$6:$F$155,$B$6:$B$155,"Educação",$C$6:$C$155,C20)>Parâmetros!$B$6),"Acima do limite","OK"))))
I21: =IF(AND(B21="",F21=""),"",IF(OR(A21="",B21="",C21="",F21="",NOT(IFERROR(OR(IFERROR(AND(LEN(SUBSTITUTE(SUBSTITUTE(SUBSTITUTE(SUBSTITUTE(E21,".",""),"-","")," ",""),"/",""))=11,SUBSTITUTE(SUBSTITUTE(SUBSTITUTE(SUBSTITUTE(E21,".",""),"-","")," ",""),"/","")<>REPT(LEFT(SUBSTITUTE(SUBSTITUTE(SUBSTITUTE(SUBSTITUTE(E21,".",""),"-","")," ",""),"/",""),1),11),VALUE(MID(SUBSTITUTE(SUBSTITUTE(SUBSTITUTE(SUBSTITUTE(E21,".",""),"-","")," ",""),"/",""),10,1))=IF(MOD(SUMPRODUCT(--MID(SUBSTITUTE(SUBSTITUTE(SUBSTITUTE(SUBSTITUTE(E21,".",""),"-","")," ",""),"/",""),{1,2,3,4,5,6,7,8,9},1),{10,9,8,7,6,5,4,3,2}),11)<2,0,11-MOD(SUMPRODUCT(--MID(SUBSTITUTE(SUBSTITUTE(SUBSTITUTE(SUBSTITUTE(E21,".",""),"-","")," ",""),"/",""),{1,2,3,4,5,6,7,8,9},1),{10,9,8,7,6,5,4,3,2}),11)),VALUE(MID(SUBSTITUTE(SUBSTITUTE(SUBSTITUTE(SUBSTITUTE(E21,".",""),"-","")," ",""),"/",""),11,1))=IF(MOD(SUMPRODUCT(--MID(SUBSTITUTE(SUBSTITUTE(SUBSTITUTE(SUBSTITUTE(E21,".",""),"-","")," ",""),"/",""),{1,2,3,4,5,6,7,8,9,10},1),{11,10,9,8,7,6,5,4,3,2}),11)<2,0,11-MOD(SUMPRODUCT(--MID(SUBSTITUTE(SUBSTITUTE(SUBSTITUTE(SUBSTITUTE(E21,".",""),"-","")," ",""),"/",""),{1,2,3,4,5,6,7,8,9,10},1),{11,10,9,8,7,6,5,4,3,2}),11))),FALSE()),AND(LEN(SUBSTITUTE(SUBSTITUTE(SUBSTITUTE(SUBSTITUTE(E21,".",""),"-","")," ",""),"/",""))=14,ISNUMBER(VALUE(SUBSTITUTE(SUBSTITUTE(SUBSTITUTE(SUBSTITUTE(E21,".",""),"-","")," ",""),"/",""))))),FALSE()))),"Revisar",IF(G21<>"Sim","Falta comprovante",IF(AND(B21="Educação",SUMIFS($F$6:$F$155,$B$6:$B$155,"Educação",$C$6:$C$155,C21)>Parâmetros!$B$6),"Acima do limite","OK"))))
... I155: =IF(AND(B155="",F155=""),"",IF(OR(A155="",B155="",C155="",F155="",NOT(IFERROR(OR(IFERROR(AND(LEN(SUBSTITUTE(SUBSTITUTE(SUBSTITUTE(SUBSTITUTE(E155,".",""),"-","")," ",""),"/",""))=11,SUBSTITUTE(SUBSTITUTE(SUBSTITUTE(SUBSTITUTE(E155,".",""),"-","")," ",""),"/","")<>REPT(LEFT(SUBSTITUTE(SUBSTITUTE(SUBSTITUTE(SUBSTITUTE(E155,".",""),"-","")," ",""),"/",""),1),11),VALUE(MID(SUBSTITUTE(SUBSTITUTE(SUBSTITUTE(SUBSTITUTE(E155,".",""),"-","")," ",""),"/",""),10,1))=IF(MOD(SUMPRODUCT(--MID(SUBSTITUTE(SUBSTITUTE(SUBSTITUTE(SUBSTITUTE(E155,".",""),"-","")," ",""),"/",""),{1,2,3,4,5,6,7,8,9},1),{10,9,8,7,6,5,4,3,2}),11)<2,0,11-MOD(SUMPRODUCT(--MID(SUBSTITUTE(SUBSTITUTE(SUBSTITUTE(SUBSTITUTE(E155,".",""),"-","")," ",""),"/",""),{1,2,3,4,5,6,7,8,9},1),{10,9,8,7,6,5,4,3,2}),11)),VALUE(MID(SUBSTITUTE(SUBSTITUTE(SUBSTITUTE(SUBSTITUTE(E155,".",""),"-","")," ",""),"/",""),11,1))=IF(MOD(SUMPRODUCT(--MID(SUBSTITUTE(SUBSTITUTE(SUBSTITUTE(SUBSTITUTE(E155,".",""),"-","")," ",""),"/",""),{1,2,3,4,5,6,7,8,9,10},1),{11,10,9,8,7,6,5,4,3,2}),11)<2,0,11-MOD(SUMPRODUCT(--MID(SUBSTITUTE(SUBSTITUTE(SUBSTITUTE(SUBSTITUTE(E155,".",""),"-","")," ",""),"/",""),{1,2,3,4,5,6,7,8,9,10},1),{11,10,9,8,7,6,5,4,3,2}),11))),FALSE()),AND(LEN(SUBSTITUTE(SUBSTITUTE(SUBSTITUTE(SUBSTITUTE(E155,".",""),"-","")," ",""),"/",""))=14,ISNUMBER(VALUE(SUBSTITUTE(SUBSTITUTE(SUBSTITUTE(SUBSTITUTE(E155,".",""),"-","")," ",""),"/",""))))),FALSE()))),"Revisar",IF(G155<>"Sim","Falta comprovante",IF(AND(B155="Educação",SUMIFS($F$6:$F$155,$B$6:$B$155,"Educação",$C$6:$C$155,C155)>Parâmetros!$B$6),"Acima do limite","OK"))))

Sheet Bens e Direitos
A1: ◄ Voltar ao Menu
A2: Bens e Direitos
A3: Informe o valor em 31/12 do ano anterior e em 31/12 do ano-calendário. Bens baixados no ano: valor atual 0.
A5: Grupo | B5: Descrição | C5: Instituição ou localização | D5: Valor em 31/12 do ano anterior (R$) | E5: Valor em 31/12 do ano-calendário (R$) | F5: Variação (R$) | G5: Status
A6: 02 Bens móveis | B6: Veículo (exemplo) | C6: Garagem | D6: 40000 | E6: 36000 | F6: =IF(AND(D6="",E6=""),"",N(E6)-N(D6)) -> -4000 | G6: =IF(AND(A6="",B6="",E6=""),"",IF(OR(A6="",B6="",E6=""),"Revisar","OK")) -> OK
A7: 06 Depósitos à vista e numerário | B7: Conta corrente (exemplo) | C7: Banco Exemplo S.A. | D7: 5000 | E7: 8200 | F7: =IF(AND(D7="",E7=""),"",N(E7)-N(D7)) -> 3200 | G7: =IF(AND(A7="",B7="",E7=""),"",IF(OR(A7="",B7="",E7=""),"Revisar","OK")) -> OK
F8: =IF(AND(D8="",E8=""),"",N(E8)-N(D8)) | G8: =IF(AND(A8="",B8="",E8=""),"",IF(OR(A8="",B8="",E8=""),"Revisar","OK"))
F9: =IF(AND(D9="",E9=""),"",N(E9)-N(D9)) | G9: =IF(AND(A9="",B9="",E9=""),"",IF(OR(A9="",B9="",E9=""),"Revisar","OK"))
F10: =IF(AND(D10="",E10=""),"",N(E10)-N(D10)) | G10: =IF(AND(A10="",B10="",E10=""),"",IF(OR(A10="",B10="",E10=""),"Revisar","OK"))
F11: =IF(AND(D11="",E11=""),"",N(E11)-N(D11)) | G11: =IF(AND(A11="",B11="",E11=""),"",IF(OR(A11="",B11="",E11=""),"Revisar","OK"))
F12: =IF(AND(D12="",E12=""),"",N(E12)-N(D12)) | G12: =IF(AND(A12="",B12="",E12=""),"",IF(OR(A12="",B12="",E12=""),"Revisar","OK"))
F13: =IF(AND(D13="",E13=""),"",N(E13)-N(D13)) | G13: =IF(AND(A13="",B13="",E13=""),"",IF(OR(A13="",B13="",E13=""),"Revisar","OK"))
F14: =IF(AND(D14="",E14=""),"",N(E14)-N(D14)) | G14: =IF(AND(A14="",B14="",E14=""),"",IF(OR(A14="",B14="",E14=""),"Revisar","OK"))
F15: =IF(AND(D15="",E15=""),"",N(E15)-N(D15)) | G15: =IF(AND(A15="",B15="",E15=""),"",IF(OR(A15="",B15="",E15=""),"Revisar","OK"))
F16: =IF(AND(D16="",E16=""),"",N(E16)-N(D16)) | G16: =IF(AND(A16="",B16="",E16=""),"",IF(OR(A16="",B16="",E16=""),"Revisar","OK"))
F17: =IF(AND(D17="",E17=""),"",N(E17)-N(D17)) | G17: =IF(AND(A17="",B17="",E17=""),"",IF(OR(A17="",B17="",E17=""),"Revisar","OK"))
F18: =IF(AND(D18="",E18=""),"",N(E18)-N(D18)) | G18: =IF(AND(A18="",B18="",E18=""),"",IF(OR(A18="",B18="",E18=""),"Revisar","OK"))
F19: =IF(AND(D19="",E19=""),"",N(E19)-N(D19)) | G19: =IF(AND(A19="",B19="",E19=""),"",IF(OR(A19="",B19="",E19=""),"Revisar","OK"))
... F65: =IF(AND(D65="",E65=""),"",N(E65)-N(D65)) | G65: =IF(AND(A65="",B65="",E65=""),"",IF(OR(A65="",B65="",E65=""),"Revisar","OK"))

Sheet Dívidas
A1: ◄ Voltar ao Menu
A2: Dívidas e ônus reais
A3: Financiamentos, empréstimos e outras obrigações. Informe o saldo devedor em 31/12 dos dois anos.
A5: Credor | B5: Descrição | C5: Saldo em 31/12 do ano anterior (R$) | D5: Saldo em 31/12 do ano-calendário (R$) | E5: Variação (R$) | F5: Status
A6: Financeira Exemplo | B6: Financiamento (exemplo) | C6: 15000 | D6: 11000 | E6: =IF(AND(C6="",D6=""),"",N(D6)-N(C6)) -> -4000 | F6: =IF(AND(A6="",C6="",D6=""),"",IF(OR(A6="",D6=""),"Revisar","OK")) -> OK
E7: =IF(AND(C7="",D7=""),"",N(D7)-N(C7)) | F7: =IF(AND(A7="",C7="",D7=""),"",IF(OR(A7="",D7=""),"Revisar","OK"))
E8: =IF(AND(C8="",D8=""),"",N(D8)-N(C8)) | F8: =IF(AND(A8="",C8="",D8=""),"",IF(OR(A8="",D8=""),"Revisar","OK"))
E9: =IF(AND(C9="",D9=""),"",N(D9)-N(C9)) | F9: =IF(AND(A9="",C9="",D9=""),"",IF(OR(A9="",D9=""),"Revisar","OK"))
E10: =IF(AND(C10="",D10=""),"",N(D10)-N(C10)) | F10: =IF(AND(A10="",C10="",D10=""),"",IF(OR(A10="",D10=""),"Revisar","OK"))
E11: =IF(AND(C11="",D11=""),"",N(D11)-N(C11)) | F11: =IF(AND(A11="",C11="",D11=""),"",IF(OR(A11="",D11=""),"Revisar","OK"))
E12: =IF(AND(C12="",D12=""),"",N(D12)-N(C12)) | F12: =IF(AND(A12="",C12="",D12=""),"",IF(OR(A12="",D12=""),"Revisar","OK"))
E13: =IF(AND(C13="",D13=""),"",N(D13)-N(C13)) | F13: =IF(AND(A13="",C13="",D13=""),"",IF(OR(A13="",D13=""),"Revisar","OK"))
E14: =IF(AND(C14="",D14=""),"",N(D14)-N(C14)) | F14: =IF(AND(A14="",C14="",D14=""),"",IF(OR(A14="",D14=""),"Revisar","OK"))
E15: =IF(AND(C15="",D15=""),"",N(D15)-N(C15)) | F15: =IF(AND(A15="",C15="",D15=""),"",IF(OR(A15="",D15=""),"Revisar","OK"))
E16: =IF(AND(C16="",D16=""),"",N(D16)-N(C16)) | F16: =IF(AND(A16="",C16="",D16=""),"",IF(OR(A16="",D16=""),"Revisar","OK"))
E17: =IF(AND(C17="",D17=""),"",N(D17)-N(C17)) | F17: =IF(AND(A17="",C17="",D17=""),"",IF(OR(A17="",D17=""),"Revisar","OK"))
E18: =IF(AND(C18="",D18=""),"",N(D18)-N(C18)) | F18: =IF(AND(A18="",C18="",D18=""),"",IF(OR(A18="",D18=""),"Revisar","OK"))
... E35: =IF(AND(C35="",D35=""),"",N(D35)-N(C35)) | F35: =IF(AND(A35="",C35="",D35=""),"",IF(OR(A35="",D35=""),"Revisar","OK"))

Sheet Checklist
A1: ◄ Voltar ao Menu
A2: Checklist de documentos
A3: Marque o que já está em mãos. Documentos obrigatórios não recebidos aparecem como pendência.
A5: Documento | B5: Obrigatório? | C5: Recebido? | D5: Observação | E5: Status
A6: Informes de rendimentos dos empregadores | B6: Sim | C6: Sim | E6: =IF(A6="","",IF(C6="Sim","OK",IF(B6="Sim","Pendente","Opcional"))) -> OK
A7: Informes de rendimentos de bancos e corretoras | B7: Sim | C7: Sim | E7: =IF(A7="","",IF(C7="Sim","OK",IF(B7="Sim","Pendente","Opcional"))) -> OK
A8: Termo de rescisão e extrato do FGTS | B8: Não | C8: Não | E8: =IF(A8="","",IF(C8="Sim","OK",IF(B8="Sim","Pendente","Opcional"))) -> Opcional
A9: Comprovante do seguro-desemprego | B9: Não | C9: Não | E9: =IF(A9="","",IF(C9="Sim","OK",IF(B9="Sim","Pendente","Opcional"))) -> Opcional
A10: Recibos e notas de despesas médicas | B10: Não | C10: Sim | E10: =IF(A10="","",IF(C10="Sim","OK",IF(B10="Sim","Pendente","Opcional"))) -> OK
A11: Comprovantes de mensalidades escolares | B11: Não | C11: Sim | E11: =IF(A11="","",IF(C11="Sim","OK",IF(B11="Sim","Pendente","Opcional"))) -> OK
A12: Informe do plano de saúde | B12: Não | C12: Não | E12: =IF(A12="","",IF(C12="Sim","OK",IF(B12="Sim","Pendente","Opcional"))) -> Opcional
A13: Informe ou extrato do PGBL | B13: Não | C13: Não | E13: =IF(A13="","",IF(C13="Sim","OK",IF(B13="Sim","Pendente","Opcional"))) -> Opcional
A14: Documentos de bens (veículo, imóvel) | B14: Sim | C14: Sim | E14: =IF(A14="","",IF(C14="Sim","OK",IF(B14="Sim","Pendente","Opcional"))) -> OK
A15: Extrato de dívidas e financiamentos | B15: Não | C15: Sim | E15: =IF(A15="","",IF(C15="Sim","OK",IF(B15="Sim","Pendente","Opcional"))) -> OK
A16: CPF e nascimento dos dependentes | B16: Sim | C16: Sim | E16: =IF(A16="","",IF(C16="Sim","OK",IF(B16="Sim","Pendente","Opcional"))) -> OK
A17: Recibos de pensão alimentícia paga | B17: Não | C17: Não | E17: =IF(A17="","",IF(C17="Sim","OK",IF(B17="Sim","Pendente","Opcional"))) -> Opcional
E18: =IF(A18="","",IF(C18="Sim","OK",IF(B18="Sim","Pendente","Opcional")))
E19: =IF(A19="","",IF(C19="Sim","OK",IF(B19="Sim","Pendente","Opcional")))
E20: =IF(A20="","",IF(C20="Sim","OK",IF(B20="Sim","Pendente","Opcional")))
E21: =IF(A21="","",IF(C21="Sim","OK",IF(B21="Sim","Pendente","Opcional")))
E22: =IF(A22="","",IF(C22="Sim","OK",IF(B22="Sim","Pendente","Opcional")))
E23: =IF(A23="","",IF(C23="Sim","OK",IF(B23="Sim","Pendente","Opcional")))
E24: =IF(A24="","",IF(C24="Sim","OK",IF(B24="Sim","Pendente","Opcional")))
E25: =IF(A25="","",IF(C25="Sim","OK",IF(B25="Sim","Pendente","Opcional")))

Sheet Resumo
A1: ◄ Voltar ao Menu
A2: Resumo e verificações
A3: Tudo aqui é calculado a partir das outras abas. Não digite nada nesta página.
A5: 1. Rendimentos do ano-calendário
A6: Rendimentos tributáveis | B6: =SUMIFS(Rendimentos!$F$6:$F$105,Rendimentos!$E$6:$E$105,"Tributável") -> 78000
A7: Sujeitos à tributação exclusiva na fonte | B7: =SUMIFS(Rendimentos!$F$6:$F$105,Rendimentos!$E$6:$E$105,"Exclusivo na fonte") -> 7700
A8: Isentos e não tributáveis | B8: =SUMIFS(Rendimentos!$F$6:$F$105,Rendimentos!$E$6:$E$105,"Isento ou não tributável") -> 12000
A9: A conferir (classe indefinida) | B9: =SUMIFS(Rendimentos!$F$6:$F$105,Rendimentos!$E$6:$E$105,"Conferir") -> 0 | C9: Confirme a classificação no programa da Receita
A10: Imposto retido na fonte | B10: =SUM(Rendimentos!$G$6:$G$105) -> 5330
A12: 2. Deduções estimadas
A13: Previdência oficial (INSS retido + carnê ou GPS) | B13: =SUM(Rendimentos!$H$6:$H$105)+SUMIFS(Deduções!$F$6:$F$155,Deduções!$B$6:$B$155,"Previdência oficial (carnê ou GPS)") -> 8556
A14: Dependentes | B14: =COUNTA(Dependentes!$A$6:$A$15)*Parâmetros!$B$7 -> 2275.08
A15: Saúde (sem limite) | B15: =SUMIFS(Deduções!$F$6:$F$155,Deduções!$B$6:$B$155,"Saúde") -> 3200
A16: Educação (limitada por pessoa) | B16: =SUM(C50:C60) -> 3561.5 | C16: Ver quadro de educação por pessoa, mais abaixo
A17: Previdência privada PGBL (até o limite) | B17: =MIN(SUMIFS(Deduções!$F$6:$F$155,Deduções!$B$6:$B$155,"Previdência privada (PGBL)"),Parâmetros!$B$8*B6) -> 3000
A18: Pensão alimentícia judicial | B18: =SUMIFS(Deduções!$F$6:$F$155,Deduções!$B$6:$B$155,"Pensão alimentícia judicial") -> 0
A19: Total de deduções estimadas | B19: =SUM(B13:B18) -> 20592.58
A20: Base estimada (tributáveis − deduções) | B20: =MAX(0,B6-B19) -> 57407.42 | C20: Antes da tabela do imposto e do desconto simplificado. Não é o imposto devido.
A22: 3. Patrimônio
A23: Bens e direitos em 31/12 do ano anterior | B23: =SUM('Bens e Direitos'!$D$6:$D$65) -> 45000
A24: Bens e direitos em 31/12 do ano-calendário | B24: =SUM('Bens e Direitos'!$E$6:$E$65) -> 44200
A25: Dívidas em 31/12 do ano anterior | B25: =SUM(Dívidas!$C$6:$C$35) -> 15000
A26: Dívidas em 31/12 do ano-calendário | B26: =SUM(Dívidas!$D$6:$D$35) -> 11000
A27: Patrimônio líquido anterior | B27: =B23-B25 -> 30000
A28: Patrimônio líquido atual | B28: =B24-B26 -> 33200
A29: Variação do patrimônio líquido | B29: =B28-B27 -> 3200
A32: 4. Verificações
A33: Verificação | B33: Ocorrências | C33: Situação | D33: Onde corrigir
A34: Contribuinte com dados incompletos ou CPF inválido | B34: =IF(OR(Contribuinte!B5="",Contribuinte!B7="",NOT(IFERROR(AND(LEN(SUBSTITUTE(SUBSTITUTE(SUBSTITUTE(SUBSTITUTE(Contribuinte!B6,".",""),"-","")," ",""),"/",""))=11,SUBSTITUTE(SUBSTITUTE(SUBSTITUTE(SUBSTITUTE(Contribuinte!B6,".",""),"-","")," ",""),"/","")<>REPT(LEFT(SUBSTITUTE(SUBSTITUTE(SUBSTITUTE(SUBSTITUTE(Contribuinte!B6,".",""),"-","")," ",""),"/",""),1),11),VALUE(MID(SUBSTITUTE(SUBSTITUTE(SUBSTITUTE(SUBSTITUTE(Contribuinte!B6,".",""),"-","")," ",""),"/",""),10,1))=IF(MOD(SUMPRODUCT(--MID(SUBSTITUTE(SUBSTITUTE(SUBSTITUTE(SUBSTITUTE(Contribuinte!B6,".",""),"-","")," ",""),"/",""),{1,2,3,4,5,6,7,8,9},1),{10,9,8,7,6,5,4,3,2}),11)<2,0,11-MOD(SUMPRODUCT(--MID(SUBSTITUTE(SUBSTITUTE(SUBSTITUTE(SUBSTITUTE(Contribuinte!B6,".",""),"-","")," ",""),"/",""),{1,2,3,4,5,6,7,8,9},1),{10,9,8,7,6,5,4,3,2}),11)),VALUE(MID(SUBSTITUTE(SUBSTITUTE(SUBSTITUTE(SUBSTITUTE(Contribuinte!B6,".",""),"-","")," ",""),"/",""),11,1))=IF(MOD(SUMPRODUCT(--MID(SUBSTITUTE(SUBSTITUTE(SUBSTITUTE(SUBSTITUTE(Contribuinte!B6,".",""),"-","")," ",""),"/",""),{1,2,3,4,5,6,7,8,9,10},1),{11,10,9,8,7,6,5,4,3,2}),11)<2,0,11-MOD(SUMPRODUCT(--MID(SUBSTITUTE(SUBSTITUTE(SUBSTITUTE(SUBSTITUTE(Contribuinte!B6,".",""),"-","")," ",""),"/",""),{1,2,3,4,5,6,7,8,9,10},1),{11,10,9,8,7,6,5,4,3,2}),11))),FALSE()))),1,0) -> 0 | C34: =IF(B34=0,"OK","Pendente") -> OK | D34: Ir para Contribuinte
A35: Dependentes com dados incompletos ou CPF inválido | B35: =COUNTIF(Dependentes!F6:F15,"Revisar") -> 0 | C35: =IF(B35=0,"OK","Pendente") -> OK | D35: Ir para Dependentes
A36: Rendimentos a revisar (campos faltando ou documento inválido) | B36: =COUNTIF(Rendimentos!K6:K105,"Revisar") -> 0 | C36: =IF(B36=0,"OK","Pendente") -> OK | D36: Ir para Rendimentos
A37: Rendimentos sem informe recebido | B37: =COUNTIF(Rendimentos!K6:K105,"Falta informe") -> 1 | C37: =IF(B37=0,"OK","Pendente") -> Pendente | D37: Ir para Rendimentos
A38: Rendimentos com classe a conferir | B38: =COUNTIF(Rendimentos!E6:E105,"Conferir") -> 0 | C38: =IF(B38=0,"OK","Aviso") -> OK | D38: Ir para Rendimentos
A39: Deduções a revisar (campos faltando ou documento inválido) | B39: =COUNTIF(Deduções!I6:I155,"Revisar") -> 0 | C39: =IF(B39=0,"OK","Pendente") -> OK | D39: Ir para Deduções
A40: Deduções sem comprovante guardado | B40: =COUNTIF(Deduções!I6:I155,"Falta comprovante") -> 1 | C40: =IF(B40=0,"OK","Pendente") -> Pendente | D40: Ir para Deduções
A41: Pessoas com despesa de educação acima do limite | B41: =COUNTIF(D50:D60,">0") -> 1 | C41: =IF(B41=0,"OK","Aviso") -> Aviso | D41: Ir para Deduções
A42: PGBL acima do limite de dedução | B42: =IF(SUMIFS(Deduções!$F$6:$F$155,Deduções!$B$6:$B$155,"Previdência privada (PGBL)")>Parâmetros!$B$8*B6,1,0) -> 0 | C42: =IF(B42=0,"OK","Aviso") -> OK | D42: Ir para Deduções
A43: Bens e dívidas a revisar | B43: =COUNTIF('Bens e Direitos'!G6:G65,"Revisar")+COUNTIF(Dívidas!F6:F35,"Revisar") -> 0 | C43: =IF(B43=0,"OK","Pendente") -> OK | D43: Ir para Bens e Direitos
A44: Documentos obrigatórios pendentes | B44: =COUNTIF(Checklist!E6:E25,"Pendente") -> 0 | C44: =IF(B44=0,"OK","Pendente") -> OK | D44: Ir para Checklist
A46: Pendências a resolver | B46: =SUMIFS(B34:B44,C34:C44,"Pendente") -> 2
A47: Avisos para conferir | B47: =COUNTIF(C34:C44,"Aviso") -> 1
A48: Educação por pessoa (limite anual por pessoa definido em Parâmetros)
A49: Beneficiário | B49: Gasto (R$) | C49: Dedutível (R$) | D49: Excedente (R$)
A50: =IF(Listas!K5="","",Listas!K5) -> Fulano de Tal (exemplo) | B50: =IF(A50="","",SUMIFS(Deduções!$F$6:$F$155,Deduções!$B$6:$B$155,"Educação",Deduções!$C$6:$C$155,A50)) -> 0 | C50: =IF(A50="","",MIN(B50,Parâmetros!$B$6)) -> 0 | D50: =IF(A50="","",B50-C50) -> 0
A51: =IF(Listas!K6="","",Listas!K6) -> Filho Exemplo | B51: =IF(A51="","",SUMIFS(Deduções!$F$6:$F$155,Deduções!$B$6:$B$155,"Educação",Deduções!$C$6:$C$155,A51)) -> 5200 | C51: =IF(A51="","",MIN(B51,Parâmetros!$B$6)) -> 3561.5 | D51: =IF(A51="","",B51-C51) -> 1638.5
A52: =IF(Listas!K7="","",Listas!K7) | B52: =IF(A52="","",SUMIFS(Deduções!$F$6:$F$155,Deduções!$B$6:$B$155,"Educação",Deduções!$C$6:$C$155,A52)) | C52: =IF(A52="","",MIN(B52,Parâmetros!$B$6)) | D52: =IF(A52="","",B52-C52)
A53: =IF(Listas!K8="","",Listas!K8) | B53: =IF(A53="","",SUMIFS(Deduções!$F$6:$F$155,Deduções!$B$6:$B$155,"Educação",Deduções!$C$6:$C$155,A53)) | C53: =IF(A53="","",MIN(B53,Parâmetros!$B$6)) | D53: =IF(A53="","",B53-C53)
A54: =IF(Listas!K9="","",Listas!K9) | B54: =IF(A54="","",SUMIFS(Deduções!$F$6:$F$155,Deduções!$B$6:$B$155,"Educação",Deduções!$C$6:$C$155,A54)) | C54: =IF(A54="","",MIN(B54,Parâmetros!$B$6)) | D54: =IF(A54="","",B54-C54)
A55: =IF(Listas!K10="","",Listas!K10) | B55: =IF(A55="","",SUMIFS(Deduções!$F$6:$F$155,Deduções!$B$6:$B$155,"Educação",Deduções!$C$6:$C$155,A55)) | C55: =IF(A55="","",MIN(B55,Parâmetros!$B$6)) | D55: =IF(A55="","",B55-C55)
A56: =IF(Listas!K11="","",Listas!K11) | B56: =IF(A56="","",SUMIFS(Deduções!$F$6:$F$155,Deduções!$B$6:$B$155,"Educação",Deduções!$C$6:$C$155,A56)) | C56: =IF(A56="","",MIN(B56,Parâmetros!$B$6)) | D56: =IF(A56="","",B56-C56)
A57: =IF(Listas!K12="","",Listas!K12) | B57: =IF(A57="","",SUMIFS(Deduções!$F$6:$F$155,Deduções!$B$6:$B$155,"Educação",Deduções!$C$6:$C$155,A57)) | C57: =IF(A57="","",MIN(B57,Parâmetros!$B$6)) | D57: =IF(A57="","",B57-C57)
A58: =IF(Listas!K13="","",Listas!K13) | B58: =IF(A58="","",SUMIFS(Deduções!$F$6:$F$155,Deduções!$B$6:$B$155,"Educação",Deduções!$C$6:$C$155,A58)) | C58: =IF(A58="","",MIN(B58,Parâmetros!$B$6)) | D58: =IF(A58="","",B58-C58)
A59: =IF(Listas!K14="","",Listas!K14) | B59: =IF(A59="","",SUMIFS(Deduções!$F$6:$F$155,Deduções!$B$6:$B$155,"Educação",Deduções!$C$6:$C$155,A59)) | C59: =IF(A59="","",MIN(B59,Parâmetros!$B$6)) | D59: =IF(A59="","",B59-C59)
A60: =IF(Listas!K15="","",Listas!K15) | B60: =IF(A60="","",SUMIFS(Deduções!$F$6:$F$155,Deduções!$B$6:$B$155,"Educação",Deduções!$C$6:$C$155,A60)) | C60: =IF(A60="","",MIN(B60,Parâmetros!$B$6)) | D60: =IF(A60="","",B60-C60)

Sheet Parâmetros
A1: ◄ Voltar ao Menu
A2: Parâmetros
A3: Parâmetro | B3: Valor | C3: Observação
A4: Ano-calendário | B4: 2026 | C4: Ano dos rendimentos e despesas que você vai declarar
A5: Exercício (ano da declaração) | B5: =B4+1 -> 2027 | C5: Calculado
A6: Limite anual de dedução com instrução, por pessoa (R$) | B6: 3561.5 | C6: Valor de referência dos últimos anos; confirmar no ano da declaração
A7: Dedução anual por dependente (R$) | B7: 2275.08 | C7: Valor de referência dos últimos anos; confirmar no ano da declaração
A8: Limite de dedução do PGBL (% dos rendimentos tributáveis) | B8: 0.12 | C8: Limite de 12% dos rendimentos tributáveis
A10: Esta ferramenta organiza dados e confere pendências. Ela não calcula o imposto devido nem substitui o programa da Receita Federal.

Sheet Listas
A1: ◄ Voltar ao Menu
A2: Listas de apoio
A3: Alimentam os menus suspensos. A classificação dos rendimentos é orientativa: confirme no programa da Receita.
A4: Tipo de rendimento | B4: Classe | D4: Tipo de dedução | F4: Parentesco | G4: Grupo de bens e direitos | I4: Sim/Não | K4: Beneficiários (automático)
A5: Salário ou pró-labore | B5: Tributável | D5: Saúde | F5: Cônjuge ou companheiro(a) | G5: 01 Bens imóveis | I5: Sim | K5: =IF(Contribuinte!B5="","",Contribuinte!B5) -> Fulano de Tal (exemplo)
A6: Férias e terço constitucional | B6: Tributável | D6: Educação | F6: Filho(a) ou enteado(a) | G6: 02 Bens móveis | I6: Não | K6: =IF(Dependentes!A6="","",Dependentes!A6) -> Filho Exemplo
A7: 13º salário | B7: Exclusivo na fonte | D7: Previdência privada (PGBL) | F7: Pai, mãe, avô ou avó | G7: 03 Participações societárias | K7: =IF(Dependentes!A7="","",Dependentes!A7)
A8: Autônomo ou RPA | B8: Tributável | D8: Previdência oficial (carnê ou GPS) | F8: Menor sob guarda | G8: 04 Aplicações e investimentos | K8: =IF(Dependentes!A8="","",Dependentes!A8)
A9: Aluguel recebido | B9: Tributável | D9: Pensão alimentícia judicial | F9: Outro | G9: 05 Créditos | K9: =IF(Dependentes!A9="","",Dependentes!A9)
A10: Aposentadoria ou pensão previdenciária | B10: Tributável | G10: 06 Depósitos à vista e numerário | K10: =IF(Dependentes!A10="","",Dependentes!A10)
A11: Pensão alimentícia recebida | B11: Tributável | G11: 07 Fundos | K11: =IF(Dependentes!A11="","",Dependentes!A11)
A12: Rendimento de aplicação financeira | B12: Exclusivo na fonte | G12: 08 Criptoativos | K12: =IF(Dependentes!A12="","",Dependentes!A12)
A13: Verbas rescisórias indenizatórias e FGTS | B13: Isento ou não tributável | G13: 99 Outros bens e direitos | K13: =IF(Dependentes!A13="","",Dependentes!A13)
A14: Seguro-desemprego | B14: Conferir | K14: =IF(Dependentes!A14="","",Dependentes!A14)
A15: Lucros e dividendos | B15: Conferir | K15: =IF(Dependentes!A15="","",Dependentes!A15)
A16: Outros rendimentos | B16: Conferir
